Workbook
Name ACTION: #REF!
Name ACTION: #REF!

Sheet Cover
B2: TEST REPORT DOCUMENT
A4: Project Name | B4: CampusStay FPT - Dormitory Registration and Room-Scheduling Management System | E4: Creator | F4: Võ Minh Luân
A5: Project Code | B5: FA26SE260 | E5: Issue Date | F5: 30/10/2026
A6: Document Code | B6: FA26SE260_TestReport_v1.0 | E6: Version | F6: 1
A9: Record of change
A10: Effective Date | B10: Version | C10: Change Item | D10: *A,D,M | E10: Change description | F10: Reference
A11: 30/10/2026 | B11: 1.0 | C11: Whole document | D11: A | E11: First version for Review 2: test cases of the mandatory features, main workflows, state transitions and NFRs; round 1 = automated run | F11: Report 3 (SRS), Report 4 (SDD), Report 5, docs/backend/04_Test_Catalog.md

Sheet Test Cases
D1: TEST CASE LIST
B3: Project Name | D3: =#REF! -> #REF!
B4: Project Code | D4: =#REF! -> #REF!
B5: Test Environment Setup Description | D5: <List enviroment requires in this system 1. Server 2. Database 3. Web Browser ... >
B8: No | C8: Function Name | D8: Sheet Name | E8: Description | F8: Pre-Condition
A9: 1 | B9: F-01 Sign-in (password, Google) | C9: F-01 | D9: Sign-in (password, Google) (FR-AUTH-01, 02); actors: All | E9: Test seed (2 Blocks, 48 students, 7 back-office users); Student signed in
A10: 2 | B10: F-02 Student accounts: verification and list import | C10: F-02 | D10: Student accounts: verification and list import (FR-AUTH-04, 05); actors: Student, Manager | E10: Test seed (2 Blocks, 48 students, 7 back-office users); Student signed in
A11: 3 | B11: F-03 Registration-period request and Term publication | C11: F-03 | D11: Registration-period request and Term publication (FR-CFG-04, 05); actors: Manager, Admin | E11: Test seed (2 Blocks, 48 students, 7 back-office users); Manager signed in
A12: 4 | B12: F-04 Apply for a Term | C12: F-04 | D12: Apply for a Term (FR-APP-01..03); actors: Student | E12: Test seed (2 Blocks, 48 students, 7 back-office users); Student signed in
A13: 5 | B13: F-05 VietQR payment claim and confirmation | C13: F-05 | D13: VietQR payment claim and confirmation (FR-BIL-01..03); actors: Student, Manager | E13: Test seed (2 Blocks, 48 students, 7 back-office users); Student signed in
A14: 6 | B14: F-06 Review, assignment and Round 2 | C14: F-06 | D14: Review, assignment and Round 2 (FR-APP-05, 07, FR-ASG-01..03); actors: Manager, Student, System | E14: Test seed (2 Blocks, 48 students, 7 back-office users); Manager signed in
A15: 7 | B15: F-07 Balance, forfeit and door code release | C15: F-07 | D15: Balance, forfeit and door code release (FR-ASG-04, 11, FR-INV-04); actors: Student, Staff, System | E15: Test seed (2 Blocks, 48 students, 7 back-office users); Student signed in
A16: 8 | B16: F-08 Check-in and check-out desk | C16: F-08 | D16: Check-in and check-out desk (FR-ASG-04, 06); actors: Staff | E16: Test seed (2 Blocks, 48 students, 7 back-office users); Staff signed in
A17: 9 | B17: F-09 Late check-in | C17: F-09 | D17: Late check-in (FR-ASG-05); actors: Student, Staff, Manager | E17: Test seed (2 Blocks, 48 students, 7 back-office users); Student signed in
A18: 10 | B18: F-10 Next-Term requests | C18: F-10 | D18: Next-Term requests (FR-REQ-01..05); actors: Student, Staff | E18: Test seed (2 Blocks, 48 students, 7 back-office users); Staff signed in
A19: 11 | B19: F-11 Requests window, reconciliation and next-Term fees | C19: F-11 | D19: Requests window, reconciliation and next-Term fees (FR-ASG-07, 08, FR-AUTH-08); actors: Manager, System | E19: Test seed (2 Blocks, 48 students, 7 back-office users); System (job) signed in
A20: 12 | B20: F-12 Turnover and operational moves | C20: F-12 | D20: Turnover and operational moves (FR-ASG-10); actors: Staff, Manager | E20: Test seed (2 Blocks, 48 students, 7 back-office users); Staff signed in
... A29: 21 | B29: Non-functional requirements | C29: NFRs | D29: NFR-01 ... NFR-06: metric, threshold and measurement method | E29: See each case

Sheet Test Statistics
B1: TEST STATISTICS
B3: Project Name | C3: CampusStay FPT - Dormitory Registration and Room-Scheduling Management System | E3: Creator
B4: Project Code | C4: FA26SE260 | E4: Reviewer/Approver
B5: Document Code | C5: FA26SE260_Test Report_v1.0 | E5: Issue Date | H5: 30/10/2026
B6: Notes | C6: Review 2 (Iteration 1): 18 mandatory features, 5 main workflows, state transitions of the main entities, 6 NFRs. Round 1 = automated run of mvn verify; manual cases pending.
B10: No | C10: Module code | D10: Passed | E10: Failed | F10: Pending | G10: N/A | H10: Number of test cases
B11: 1 | C11: F-01 Sign-in (password, Google) | D11: ='F-01'!B6 -> 4 | E11: ='F-01'!C6 -> 0 | F11: ='F-01'!D6 -> 0 | G11: ='F-01'!E6 -> 0 | H11: ='F-01'!B4 -> 4
B12: 2 | C12: F-02 Student accounts: verification and list import | D12: ='F-02'!B6 -> 6 | E12: ='F-02'!C6 -> 0 | F12: ='F-02'!D6 -> 0 | G12: ='F-02'!E6 -> 0 | H12: ='F-02'!B4 -> 6
B13: 3 | C13: F-03 Registration-period request and Term publication | D13: ='F-03'!B6 -> 5 | E13: ='F-03'!C6 -> 0 | F13: ='F-03'!D6 -> 0 | G13: ='F-03'!E6 -> 0 | H13: ='F-03'!B4 -> 5
B14: 4 | C14: F-04 Apply for a Term | D14: ='F-04'!B6 -> 5 | E14: ='F-04'!C6 -> 0 | F14: ='F-04'!D6 -> 0 | G14: ='F-04'!E6 -> 0 | H14: ='F-04'!B4 -> 5
B15: 5 | C15: F-05 VietQR payment claim and confirmation | D15: ='F-05'!B6 -> 4 | E15: ='F-05'!C6 -> 0 | F15: ='F-05'!D6 -> 0 | G15: ='F-05'!E6 -> 0 | H15: ='F-05'!B4 -> 4
B16: 6 | C16: F-06 Review, assignment and Round 2 | D16: ='F-06'!B6 -> 8 | E16: ='F-06'!C6 -> 0 | F16: ='F-06'!D6 -> 0 | G16: ='F-06'!E6 -> 0 | H16: ='F-06'!B4 -> 8
B17: 7 | C17: F-07 Balance, forfeit and door code release | D17: ='F-07'!B6 -> 5 | E17: ='F-07'!C6 -> 0 | F17: ='F-07'!D6 -> 0 | G17: ='F-07'!E6 -> 0 | H17: ='F-07'!B4 -> 5
B18: 8 | C18: F-08 Check-in and check-out desk | D18: ='F-08'!B6 -> 5 | E18: ='F-08'!C6 -> 0 | F18: ='F-08'!D6 -> 0 | G18: ='F-08'!E6 -> 0 | H18: ='F-08'!B4 -> 5
B19: 9 | C19: F-09 Late check-in | D19: ='F-09'!B6 -> 3 | E19: ='F-09'!C6 -> 0 | F19: ='F-09'!D6 -> 0 | G19: ='F-09'!E6 -> 0 | H19: ='F-09'!B4 -> 3
B20: 10 | C20: F-10 Next-Term requests | D20: ='F-10'!B6 -> 6 | E20: ='F-10'!C6 -> 0 | F20: ='F-10'!D6 -> 0 | G20: ='F-10'!E6 -> 0 | H20: ='F-10'!B4 -> 6
B21: 11 | C21: F-11 Requests window, reconciliation and next-Term fees | D21: ='F-11'!B6 -> 6 | E21: ='F-11'!C6 -> 0 | F21: ='F-11'!D6 -> 0 | G21: ='F-11'!E6 -> 0 | H21: ='F-11'!B4 -> 6
B22: 12 | C22: F-12 Turnover and operational moves | D22: ='F-12'!B6 -> 3 | E22: ='F-12'!C6 -> 0 | F22: ='F-12'!D6 -> 0 | G22: ='F-12'!E6 -> 0 | H22: ='F-12'!B4 -> 3
B23: 13 | C23: F-13 Maintenance with routing, time limits and escalation | D23: ='F-13'!B6 -> 7 | E23: ='F-13'!C6 -> 0 | F23: ='F-13'!D6 -> 0 | G23: ='F-13'!E6 -> 0 | H23: ='F-13'!B4 -> 7
B24: 14 | C24: F-14 Meter readings and Utility Invoices | D24: ='F-14'!B6 -> 4 | E24: ='F-14'!C6 -> 0 | F24: ='F-14'!D6 -> 0 | G24: ='F-14'!E6 -> 0 | H24: ='F-14'!B4 -> 4
B25: 15 | C25: F-15 Utility debt and termination | D25: ='F-15'!B6 -> 4 | E25: ='F-15'!C6 -> 0 | F25: ='F-15'!D6 -> 0 | G25: ='F-15'!E6 -> 0 | H25: ='F-15'!B4 -> 4
B26: 16 | C26: F-16 Inventory, Room Class by Term, furniture | D26: ='F-16'!B6 -> 4 | E26: ='F-16'!C6 -> 0 | F26: ='F-16'!D6 -> 0 | G26: ='F-16'!E6 -> 0 | H26: ='F-16'!B4 -> 4
B27: 17 | C27: F-17 Notifications, announcements and push | D27: ='F-17'!B6 -> 4 | E27: ='F-17'!C6 -> 0 | F27: ='F-17'!D6 -> 0 | G27: ='F-17'!E6 -> 0 | H27: ='F-17'!B4 -> 4
B28: 18 | C28: F-18 Dashboards, reports, exports and search | D28: ='F-18'!B6 -> 5 | E28: ='F-18'!C6 -> 0 | F28: ='F-18'!D6 -> 0 | G28: ='F-18'!E6 -> 0 | H28: ='F-18'!B4 -> 5
B29: 19 | C29: Main workflows (end to end) | D29: =Workflows!B6 -> 0 | E29: =Workflows!C6 -> 0 | F29: =Workflows!D6 -> 5 | G29: =Workflows!E6 -> 0 | H29: =Workflows!B4 -> 5
B30: 20 | C30: State transitions of the main entities | D30: ='State transitions'!B6 -> 59 | E30: ='State transitions'!C6 -> 0 | F30: ='State transitions'!D6 -> 11 | G30: ='State transitions'!E6 -> 0 | H30: ='State transitions'!B4 -> 70
B31: 21 | C31: Non-functional requirements | D31: =NFRs!B6 -> 2 | E31: =NFRs!C6 -> 0 | F31: =NFRs!D6 -> 4 | G31: =NFRs!E6 -> 0 | H31: =NFRs!B4 -> 6
C33: Sub total | D33: =SUM(D9:D32) -> 149 | E33: =SUM(E9:E32) -> 0 | F33: =SUM(F9:F32) -> 20 | G33: =SUM(G9:G32) -> 0 | H33: =SUM(H9:H32) -> 169
C35: Test coverage | E35: =(D33+E33)*100/(H33-G33) -> 88.16568 | F35: %
C36: Test successful coverage | E36: =D33*100/(H33-G33) -> 88.16568 | F36: %

Sheet F-01
A2: Feature | B2: F-01 Sign-in (password, Google) | R2: Passed
A3: Test requirement | B3: Sign-in (password, Google) (FR-AUTH-01, 02); actors: All | R3: Failed
A4: Number of TCs | B4: =COUNTA(A12:A1000) -> 4 | R4: Pending
A5: Testing Round | B5: Passed | C5: Failed | D5: Pending | E5: N/A | R5: N/A
A6: Round 1 | B6: =COUNTIF($F10:$F998,B5) -> 4 | C6: =COUNTIF($F10:$F998,C5) -> 0 | D6: =COUNTIF($F10:$F998,D5) -> 0 | E6: =COUNTIF($F10:$F998,E5) -> 0
A7: Round 2 | B7: 0 | C7: 0 | D7: 0 | E7: 0
A8: Round 3 | B8: 0 | C8: 0 | D8: 0 | E8: 0
A10: Test Case ID | B10: Test Case Description | C10: Test Case Procedure | D10: Expected Results | E10: Pre-conditions | F10: Round 1 | G10: Test date | H10: Tester | I10: Round 2 | J10: Test date | K10: Tester | L10: Round 3 | M10: Test date | N10: Tester | O10: Note
A11: FR-AUTH-01, 02
A12: TC-F01-01 | B12: [Main] Valid credentials return a token and the contract user shape. | C12: Automated (AuthFlowIT.signInReturnsTokenAndUser): POST /api/auth/sign-in; check the answer and the database | D12: Valid credentials return a token and the contract user shape. | E12: Test seed (2 Blocks, 48 students, 7 back-office users); Student signed in | F12: Passed | G12: 30/10/2026 | H12: CI (mvn verify)
A13: TC-F01-02 | B13: [Main] An unknown FPT Google account signs up as a student without a password; until it sets one only the setup endpoints answer; the password follows the usual rules and is set once. | C13: Automated (GoogleSignUpIT.signUpThenSetAPassword): POST /api/auth/google; POST /api/auth/password/set; GET, PUT /api/students/me/verification; check the answer and the database | D13: An unknown FPT Google account signs up as a student without a password; until it sets one only the setup endpoints answer; the password follows the usual rules and is set once. | E13: Test seed (2 Blocks, 48 students, 7 back-office users); Student signed in | F13: Passed | G13: 30/10/2026 | H13: CI (mvn verify)
A14: TC-F01-03 | B14: [Rule] The 5th wrong password locks the account, even for the right password. | C14: Automated (AuthFlowIT.accountLocksAfterMaxFailedAttempts): POST /api/auth/sign-in; check the answer and the database | D14: The 5th wrong password locks the account, even for the right password. | E14: Test seed (2 Blocks, 48 students, 7 back-office users); Student signed in | F14: Passed | G14: 30/10/2026 | H14: CI (mvn verify)
A15: TC-F01-04 | B15: [Exception] No token → 401; a student calling an Admin endpoint → 403. | C15: Automated (AuthFlowIT.roleRulesAreEnforced): GET /api/auth/me; check the answer and the database | D15: No token → 401; a student calling an Admin endpoint → 403. | E15: Test seed (2 Blocks, 48 students, 7 back-office users); Student signed in | F15: Passed | G15: 30/10/2026 | H15: CI (mvn verify)

Sheet F-02
A2: Feature | B2: F-02 Student accounts: verification and list import | R2: Passed
A3: Test requirement | B3: Student accounts: verification and list import (FR-AUTH-04, 05); actors: Student, Manager | R3: Failed
A4: Number of TCs | B4: =COUNTA(A12:A1000) -> 6 | R4: Pending
A5: Testing Round | B5: Passed | C5: Failed | D5: Pending | E5: N/A | R5: N/A
A6: Round 1 | B6: =COUNTIF($F10:$F998,B5) -> 6 | C6: =COUNTIF($F10:$F998,C5) -> 0 | D6: =COUNTIF($F10:$F998,D5) -> 0 | E6: =COUNTIF($F10:$F998,E5) -> 0
A7: Round 2 | B7: 0 | C7: 0 | D7: 0 | E7: 0
A8: Round 3 | B8: 0 | C8: 0 | D8: 0 | E8: 0
A10: Test Case ID | B10: Test Case Description | C10: Test Case Procedure | D10: Expected Results | E10: Pre-conditions | F10: Round 1 | G10: Test date | H10: Tester | I10: Round 2 | J10: Test date | K10: Tester | L10: Round 3 | M10: Test date | N10: Tester | O10: Note
A11: FR-AUTH-04, 05
A12: TC-F02-01 | B12: [Main] The sign-up form checks every field and the student code; once sent the account is Pending verification, every Manager is told, and the student cannot apply. | C12: Automated (GoogleSignUpIT.signUpFormWaitsForAManager): GET, PUT /api/students/me/verification; check the answer and the database | D12: The sign-up form checks every field and the student code; once sent the account is Pending verification, every Manager is told, and the student cannot apply. | E12: Test seed (2 Blocks, 48 students, 7 back-office users); Student signed in | F12: Passed | G12: 30/10/2026 | H12: CI (mvn verify)
A13: TC-F02-02 | B13: [Main] A Manager verifies a pending account (the student is told) or rejects it (locked); locking signs the student out until a Manager unlocks the account; a rejected account comes back as pending. | C13: Automated (StudentAccountsIT.verifyRejectLockUnlock): POST /api/student-accounts/{id}/verify; POST /api/student-accounts/{id}/reject; POST /api/student-accounts/{id}/lock; POST /api/student-accounts/{id}/unlock; check the answer and the database | D13: A Manager verifies a pending account (the student is told) or rejects it (locked); locking signs the student out until a Manager unlocks the account; a rejected account comes back as pending. | E13: Test seed (2 Blocks, 48 students, 7 back-office users); Manager signed in | F13: Passed | G13: 30/10/2026 | H13: CI (mvn verify)
A14: TC-F02-03 | B14: [Rule] The template names the columns; an upload is previewed line by line (New, Update, Unchanged, Error with the reason) and counts the students the file leaves out; nothing changes before the confirmation. | C14: Automated (StudentImportIT.previewsTheFile): GET /api/student-imports/template; POST /api/student-imports; check the answer and the database | D14: The template names the columns; an upload is previewed line by line (New, Update, Unchanged, Error with the reason) and counts the students the file leaves out; nothing changes before the confirmation. | E14: Test seed (2 Blocks, 48 students, 7 back-office users); Manager signed in | F14: Passed | G14: 30/10/2026 | H14: CI (mvn verify)
A15: TC-F02-04 | B15: [Main] Confirming creates and updates the accounts, verifies the waiting one that matches, gives a fictional student's code to the real student, marks real students missing from the file Not enrolled (never fictional ones), is written to the Audit Log and cannot run twice. | C15: Automated (StudentImportIT.confirmAppliesTheFile): GET /api/student-imports; POST /api/student-imports/{id}/confirm; check the answer and the database | D15: Confirming creates and updates the accounts, verifies the waiting one that matches, gives a fictional student's code to the real student, marks real students missing from the file Not enrolled (never fictional ones), is written to the Audit Log and cannot run twice. | E15: Test seed (2 Blocks, 48 students, 7 back-office users); Manager signed in | F15: Passed | G15: 30/10/2026 | H15: CI (mvn verify)
A16: TC-F02-05 | B16: [Rule] A major is read from its code, its English label or its Vietnamese name, the other FPT majors are in the list (V61), and a student-code prefix such as SS put in the major column gets an error that says so; the file is the XLSX the template writer makes. | C16: Automated (StudentImportIT.readsMajorsByCodeOrNameAndExplainsCodePrefixes): run the scenario and check the result | D16: A major is read from its code, its English label or its Vietnamese name, the other FPT majors are in the list (V61), and a student-code prefix such as SS put in the major column gets an error that says so; the file is the XLSX the template writer makes. | E16: Test seed (2 Blocks, 48 students, 7 back-office users); Manager signed in | F16: Passed | G16: 30/10/2026 | H16: CI (mvn verify)
A17: TC-F02-06 | B17: [Exception] Only a verified account may apply: a pending one sees why and is refused (ADR-26). | C17: Automated (StudentAccountsIT.pendingAccountCannotApply): POST /api/student-accounts/{id}/verify; check the answer and the database | D17: Only a verified account may apply: a pending one sees why and is refused (ADR-26). | E17: Test seed (2 Blocks, 48 students, 7 back-office users); Student signed in | F17: Passed | G17: 30/10/2026 | H17: CI (mvn verify)

Sheet F-03
A2: Feature | B2: F-03 Registration-period request and Term publication | R2: Passed
A3: Test requirement | B3: Registration-period request and Term publication (FR-CFG-04, 05); actors: Manager, Admin | R3: Failed
A4: Number of TCs | B4: =COUNTA(A12:A1000) -> 5 | R4: Pending
A5: Testing Round | B5: Passed | C5: Failed | D5: Pending | E5: N/A | R5: N/A
A6: Round 1 | B6: =COUNTIF($F10:$F998,B5) -> 5 | C6: =COUNTIF($F10:$F998,C5) -> 0 | D6: =COUNTIF($F10:$F998,D5) -> 0 | E6: =COUNTIF($F10:$F998,E5) -> 0
A7: Round 2 | B7: 0 | C7: 0 | D7: 0 | E7: 0
A8: Round 3 | B8: 0 | C8: 0 | D8: 0 | E8: 0
A10: Test Case ID | B10: Test Case Description | C10: Test Case Procedure | D10: Expected Results | E10: Pre-conditions | F10: Round 1 | G10: Test date | H10: Tester | I10: Round 2 | J10: Test date | K10: Tester | L10: Round 3 | M10: Test date | N10: Tester | O10: Note
A11: FR-CFG-04, 05
A12: TC-F03-01 | B12: [Main] A Manager files a request; it is Submitted with its proposal and history, every Admin and every other Manager is notified with a link to the requests list, and the requester is not. | C12: Automated (TermRequestIT.managerFilesARequest): GET /api/term-requests; GET /api/term-requests/{id}; POST /api/term-requests; check the answer and the database | D12: A Manager files a request; it is Submitted with its proposal and history, every Admin and every other Manager is notified with a link to the requests list, and the requester is not. | E12: Test seed (2 Blocks, 48 students, 7 back-office users); Manager signed in | F12: Passed | G12: 30/10/2026 | H12: CI (mvn verify)
A13: TC-F03-02 | B13: [Main] The Admin builds the Draft from a Manager's request: it holds the request's dates, Blocks, Rooms and prices, the request is In progress (the Manager is told) and building again opens the same Draft; a price that differs from the request needs a reason, which the request then shows next to the difference. | C13: Automated (TermWizardIT.buildsTheTermFromARequest): GET /api/term-requests/{id}; POST /api/admin/terms/drafts; GET /api/admin/terms/{id}/wizard; PUT /api/admin/terms/{id}/wizard/{step}; check the answer and the database | D13: The Admin builds the Draft from a Manager's request: it holds the request's dates, Blocks, Rooms and prices, the request is In progress (the Manager is told) and building again opens the same Draft; a price that differs from the request needs a reason, which the request then shows next to the difference. | E13: Test seed (2 Blocks, 48 students, 7 back-office users); Admin signed in | F13: Passed | G13: 30/10/2026 | H13: CI (mvn verify)
A14: TC-F03-03 | B14: [Rule] The Timeline step checks spec §5.2 per field: registration closing before it opens, renewal milestones filled in only partly or out of order, Check-in before the Term before is left. | C14: Automated (TermWizardIT.timelineFollowsTheRules): POST /api/admin/terms/drafts; PUT /api/admin/terms/{id}/wizard/{step}; check the answer and the database | D14: The Timeline step checks spec §5.2 per field: registration closing before it opens, renewal milestones filled in only partly or out of order, Check-in before the Term before is left. | E14: Test seed (2 Blocks, 48 students, 7 back-office users); Admin signed in | F14: Passed | G14: 30/10/2026 | H14: CI (mvn verify)
A15: TC-F03-04 | B15: [Rule] A Draft with unsaved steps cannot be published; once every step is saved, publishing fixes the Term's prices, Deposit and rules, tells every Manager (Term dashboard link) and puts the Term announcement on the students' board and bell. A later default-price change leaves the Term's prices alone, an Application pays the Term's Deposit, and once an Invoice exists the prices are locked. | C15: Automated (TermWizardIT.publishingFixesTheTerm): POST /api/admin/terms/{id}/publish; GET /api/catalog; POST /api/admin/terms/drafts; GET /api/admin/terms/{id}/wizard; check the answer and the database | D15: A Draft with unsaved steps cannot be published; once every step is saved, publishing fixes the Term's prices, Deposit and rules, tells every Manager (Term dashboard link) and puts the Term announcement on the students' board and bell. A later default-price change leaves the Term's prices alone, an Application pays the Term's Deposit, and once an Invoice exists the prices are locked. | E15: Test seed (2 Blocks, 48 students, 7 back-office users); Admin signed in | F15: Passed | G15: 30/10/2026 | H15: CI (mvn verify)
A16: TC-F03-05 | B16: [Exception] Missing fields and an unknown Block are named per field; a second open request for the same Term is refused; Staff and students cannot file or read requests. | C16: Automated (TermRequestIT.refusesInvalidAndDuplicateRequests): POST /api/term-requests; check the answer and the database | D16: Missing fields and an unknown Block are named per field; a second open request for the same Term is refused; Staff and students cannot file or read requests. | E16: Test seed (2 Blocks, 48 students, 7 back-office users); Manager signed in | F16: Passed | G16: 30/10/2026 | H16: CI (mvn verify)

Sheet F-04
A2: Feature | B2: F-04 Apply for a Term | R2: Passed
A3: Test requirement | B3: Apply for a Term (FR-APP-01..03); actors: Student | R3: Failed
A4: Number of TCs | B4: =COUNTA(A12:A1000) -> 5 | R4: Pending
A5: Testing Round | B5: Passed | C5: Failed | D5: Pending | E5: N/A | R5: N/A
A6: Round 1 | B6: =COUNTIF($F10:$F998,B5) -> 5 | C6: =COUNTIF($F10:$F998,C5) -> 0 | D6: =COUNTIF($F10:$F998,D5) -> 0 | E6: =COUNTIF($F10:$F998,E5) -> 0
A7: Round 2 | B7: 0 | C7: 0 | D7: 0 | E7: 0
A8: Round 3 | B8: 0 | C8: 0 | D8: 0 | E8: 0
A10: Test Case ID | B10: Test Case Description | C10: Test Case Procedure | D10: Expected Results | E10: Pre-conditions | F10: Round 1 | G10: Test date | H10: Tester | I10: Round 2 | J10: Test date | K10: Tester | L10: Round 3 | M10: Test date | N10: Tester | O10: Note
A11: FR-APP-01..03
A12: TC-F04-01 | B12: [Main] Submit with a Deposit Invoice, then the list, detail, Home and notification; a second one is refused. | C12: Automated (ApplicationsIT.submitsApplicationWithDeposit): POST /api/applications; GET /api/applications/{id}; GET /api/students/me/applications; GET /api/students/me/home; check the answer and the database | D12: Submit with a Deposit Invoice, then the list, detail, Home and notification; a second one is refused. | E12: Test seed (2 Blocks, 48 students, 7 back-office users); Student signed in | F12: Passed | G12: 30/10/2026 | H12: CI (mvn verify)
A13: TC-F04-02 | B13: [Main] An invited pair reaches the office together: the first to pay waits as Awaiting Roommate; both are Submitted when the second Deposit is paid. | C13: Automated (ApplicationsIT.invitedPairIsSubmittedTogether): POST /api/applications; GET /api/applications/{id}; POST /api/roommate-invitations/{id}/respond; GET /api/students/me/applications; check the answer and the database | D13: An invited pair reaches the office together: the first to pay waits as Awaiting Roommate; both are Submitted when the second Deposit is paid. | E13: Test seed (2 Blocks, 48 students, 7 back-office users); Student signed in | F13: Passed | G13: 30/10/2026 | H13: CI (mvn verify)
A14: TC-F04-03 | B14: [Rule] The stay length (spec §6.6, D-13) is 1 to stay.max_terms, capped by the semesters the student has left (stay.program_semesters); it is kept on the Application and shown to the student and the back office; a student who already holds a Bed for the Term cannot apply (not a continuing resident). | C14: Automated (ApplicationsIT.stayTermsOnTheApplication): POST /api/applications; GET /api/applications/eligibility; check the answer and the database | D14: The stay length (spec §6.6, D-13) is 1 to stay.max_terms, capped by the semesters the student has left (stay.program_semesters); it is kept on the Application and shown to the student and the back office; a student who already holds a Bed for the Term cannot apply (not a continuing resident). | E14: Test seed (2 Blocks, 48 students, 7 back-office users); Student signed in | F14: Passed | G14: 30/10/2026 | H14: CI (mvn verify)
A15: TC-F04-04 | B15: [Rule] Contact, consent and roommate rules are named per field. | C15: Automated (ApplicationsIT.applicationIsValidated): POST /api/applications; check the answer and the database | D15: Contact, consent and roommate rules are named per field. | E15: Test seed (2 Blocks, 48 students, 7 back-office users); Student signed in | F15: Passed | G15: 30/10/2026 | H15: CI (mvn verify)
A16: TC-F04-05 | B16: [Exception] Staff cannot use student screens; another student's Application is 404. | C16: Automated (ApplicationsIT.applicationsArePrivate): GET /api/applications/{id}; POST /api/applications/{id}/cancel; GET /api/students/me/home; GET /api/students/me/profile; check the answer and the database | D16: Staff cannot use student screens; another student's Application is 404. | E16: Test seed (2 Blocks, 48 students, 7 back-office users); Staff signed in | F16: Passed | G16: 30/10/2026 | H16: CI (mvn verify)

Sheet F-05
A2: Feature | B2: F-05 VietQR payment claim and confirmation | R2: Passed
A3: Test requirement | B3: VietQR payment claim and confirmation (FR-BIL-01..03); actors: Student, Manager | R3: Failed
A4: Number of TCs | B4: =COUNTA(A12:A1000) -> 4 | R4: Pending
A5: Testing Round | B5: Passed | C5: Failed | D5: Pending | E5: N/A | R5: N/A
A6: Round 1 | B6: =COUNTIF($F10:$F998,B5) -> 4 | C6: =COUNTIF($F10:$F998,C5) -> 0 | D6: =COUNTIF($F10:$F998,D5) -> 0 | E6: =COUNTIF($F10:$F998,E5) -> 0
A7: Round 2 | B7: 0 | C7: 0 | D7: 0 | E7: 0
A8: Round 3 | B8: 0 | C8: 0 | D8: 0 | E8: 0
A10: Test Case ID | B10: Test Case Description | C10: Test Case Procedure | D10: Expected Results | E10: Pre-conditions | F10: Round 1 | G10: Test date | H10: Tester | I10: Round 2 | J10: Test date | K10: Tester | L10: Round 3 | M10: Test date | N10: Tester | O10: Note
A11: FR-BIL-01..03
A12: TC-F05-01 | B12: [Main] The claim waits for a Manager and stops the Deposit window (the Application does not expire); the queue lists it with the count and total; a bulk confirmation pays each Invoice at the time of its claim, one audit entry each, and the Applications are submitted; unknown Invoices are skipped. | C12: Automated (PaymentClaimIT.claimStopsTheClockAndBulkConfirmationPays): GET /api/invoices/{id}/payment; GET /api/students/me/invoices; POST /api/invoices/{id}/claim; GET /api/payment-claims; check the answer and the database | D12: The claim waits for a Manager and stops the Deposit window (the Application does not expire); the queue lists it with the count and total; a bulk confirmation pays each Invoice at the time of its claim, one audit entry each, and the Applications are submitted; unknown Invoices are skipped. | E12: Test seed (2 Blocks, 48 students, 7 back-office users); Student signed in | F12: Passed | G12: 30/10/2026 | H12: CI (mvn verify)
A13: TC-F05-02 | B13: [Main] A student reads and saves their refund account; the number keeps its digits only, each field is checked, and only students have one. | C13: Automated (RefundAccountIT.studentKeepsTheirRefundAccount): GET /api/students/me/refund-account; PUT /api/students/me/refund-account; check the answer and the database | D13: A student reads and saves their refund account; the number keeps its digits only, each field is checked, and only students have one. | E13: Test seed (2 Blocks, 48 students, 7 back-office users); Student signed in | F13: Passed | G13: 30/10/2026 | H13: CI (mvn verify)
A14: TC-F05-03 | B14: [Rule] A rejection needs a reason; the Invoice is Unpaid again and the deadline continues with the time that was left (at least payment.rejected_claim_min_hours); the student is told; a second rejection cancels the Deposit and the Application expires. | C14: Automated (PaymentClaimIT.rejectionsGiveTimeBackThenCancel): GET /api/invoices/{id}/payment; POST /api/invoices/{id}/claim; POST /api/payment-claims/reject; check the answer and the database | D14: A rejection needs a reason; the Invoice is Unpaid again and the deadline continues with the time that was left (at least payment.rejected_claim_min_hours); the student is told; a second rejection cancels the Deposit and the Application expires. | E14: Test seed (2 Blocks, 48 students, 7 back-office users); Manager signed in | F14: Passed | G14: 30/10/2026 | H14: CI (mvn verify)
A15: TC-F05-04 | B15: [Exception] One claim at a time; a paid or void Invoice and a Deposit past its deadline cannot be claimed; a student cannot cancel while a claim waits; only Managers see the queue and decide; an empty selection is refused; Invoices without a claim are skipped. | C15: Automated (PaymentClaimIT.claimRules): POST /api/invoices/{id}/claim; GET /api/payment-claims; POST /api/payment-claims/confirm; POST /api/payment-claims/reject; check the answer and the database | D15: One claim at a time; a paid or void Invoice and a Deposit past its deadline cannot be claimed; a student cannot cancel while a claim waits; only Managers see the queue and decide; an empty selection is refused; Invoices without a claim are skipped. | E15: Test seed (2 Blocks, 48 students, 7 back-office users); Student signed in | F15: Passed | G15: 30/10/2026 | H15: CI (mvn verify)

Sheet F-06
A2: Feature | B2: F-06 Review, assignment and Round 2 | R2: Passed
A3: Test requirement | B3: Review, assignment and Round 2 (FR-APP-05, 07, FR-ASG-01..03); actors: Manager, Student, System | R3: Failed
A4: Number of TCs | B4: =COUNTA(A12:A1000) -> 8 | R4: Pending
A5: Testing Round | B5: Passed | C5: Failed | D5: Pending | E5: N/A | R5: N/A
A6: Round 1 | B6: =COUNTIF($F10:$F998,B5) -> 8 | C6: =COUNTIF($F10:$F998,C5) -> 0 | D6: =COUNTIF($F10:$F998,D5) -> 0 | E6: =COUNTIF($F10:$F998,E5) -> 0
A7: Round 2 | B7: 0 | C7: 0 | D7: 0 | E7: 0
A8: Round 3 | B8: 0 | C8: 0 | D8: 0 | E8: 0
A10: Test Case ID | B10: Test Case Description | C10: Test Case Procedure | D10: Expected Results | E10: Pre-conditions | F10: Round 1 | G10: Test date | H10: Tester | I10: Round 2 | J10: Test date | K10: Tester | L10: Round 3 | M10: Test date | N10: Tester | O10: Note
A11: FR-APP-05, 07, FR-ASG-01..03
A12: TC-F06-01 | B12: [Main] The Manager approves in bulk, runs, resolves the conflict to the waitlist and commits the Block, which approves it at once (ADR-19): Allocations, Balance Invoices, notifications and My Room. Staff cannot commit. | C12: Automated (AssignmentIT.assignmentRunToAllocation): GET /api/students/me/home; POST /api/applications/bulk-review; GET /api/approvals/assignment; GET /api/assignment-runs; check the answer and the database | D12: The Manager approves in bulk, runs, resolves the conflict to the waitlist and commits the Block, which approves it at once (ADR-19): Allocations, Balance Invoices, notifications and My Room. Staff cannot commit. | E12: Test seed (2 Blocks, 48 students, 7 back-office users); Manager signed in | F12: Passed | G12: 30/10/2026 | H12: CI (mvn verify)
A13: TC-F06-02 | B13: [Main] A Manager runs Round 2 (M8): the Waitlisted students without an open offer get held options on the Term's free Beds, by the rules of the offers made when a Block is approved; students may not run it. The Manager's list shows who is waiting without an offer, then who got one with its options (A-58). | C13: Automated (Round2IT.managerRunsRound2): GET /api/round2; POST /api/round2/run; GET /api/round2/offers; check the answer and the database | D13: A Manager runs Round 2 (M8): the Waitlisted students without an open offer get held options on the Term's free Beds, by the rules of the offers made when a Block is approved; students may not run it. The Manager's list shows who is waiting without an offer, then who got one with its options (A-58). | E13: Test seed (2 Blocks, 48 students, 7 back-office users); Manager signed in | F13: Passed | G13: 30/10/2026 | H13: CI (mvn verify)
A14: TC-F06-03 | B14: [Main] A waitlisted student sees the open offer, the day the waitlist ends and the refund; withdrawing closes the offer, releases its Beds, cancels the Application and asks a Manager to refund the whole Deposit, whose list shows the student's bank account (A-61, A-62). A plain cancel is refused, and only one's own waitlisted Application can be withdrawn. | C14: Automated (Round2IT.waitlistedStudentWithdraws): POST /api/applications/{id}/withdraw; PUT /api/students/me/refund-account; check the answer and the database | D14: A waitlisted student sees the open offer, the day the waitlist ends and the refund; withdrawing closes the offer, releases its Beds, cancels the Application and asks a Manager to refund the whole Deposit, whose list shows the student's bank account (A-61, A-62). A plain cancel is refused, and only one's own waitlisted Application can be withdrawn. | E14: Test seed (2 Blocks, 48 students, 7 back-office users); Student signed in | F14: Passed | G14: 30/10/2026 | H14: CI (mvn verify)
A15: TC-F06-04 | B15: [Rule] The queue, the review view (opening it starts the review), rejection needs a note, once only. | C15: Automated (AssignmentIT.reviewQueueAndRejection): GET /api/applications/{id}; GET /api/applications; POST /api/applications/{id}/review; check the answer and the database | D15: The queue, the review view (opening it starts the review), rejection needs a note, once only. | E15: Test seed (2 Blocks, 48 students, 7 back-office users); Manager signed in | F15: Passed | G15: 30/10/2026 | H15: CI (mvn verify)
A16: TC-F06-05 | B16: [Rule] The priority group goes first; the same input gives the same proposal. | C16: Automated (AssignmentEngineTest.priorityOrderAndDeterminism): POST /api/assignment-runs; check the answer and the database | D16: The priority group goes first; the same input gives the same proposal. | E16: Test seed (2 Blocks, 48 students, 7 back-office users); Manager signed in | F16: Passed | G16: 30/10/2026 | H16: CI (mvn verify)
A17: TC-F06-06 | B17: [Rule] When the Term's check-in starts, a waitlisted Application without an open offer is cancelled with the whole Deposit to refund and the student is told; one with an open offer keeps it until it is answered. | C17: Automated (Round2IT.waitlistEndsWhenCheckInStarts): run the scenario and check the result | D17: When the Term's check-in starts, a waitlisted Application without an open offer is cancelled with the whole Deposit to refund and the student is told; one with an open offer keeps it until it is answered. | E17: Test seed (2 Blocks, 48 students, 7 back-office users); System (job) signed in | F17: Passed | G17: 30/10/2026 | H17: CI (mvn verify)
A18: TC-F06-07 | B18: [Exception] A dry run is a preview; students and Staff cannot use runs (ADR-19). | C18: Automated (AssignmentIT.dryRunAndPermissions): GET /api/approvals/assignment; GET /api/assignment-runs; POST /api/assignment-runs; POST /api/assignment-runs/{runId}/commit; check the answer and the database | D18: A dry run is a preview; students and Staff cannot use runs (ADR-19). | E18: Test seed (2 Blocks, 48 students, 7 back-office users); Staff signed in | F18: Passed | G18: 30/10/2026 | H18: CI (mvn verify)
A19: TC-F06-08 | B19: [Exception] Every Manager sees every Block's Applications (ADR-19); Staff and students cannot review. | C19: Automated (AssignmentIT.reviewIsScopedByBlock): GET /api/applications/{id}; GET /api/applications; POST /api/applications/{id}/review; check the answer and the database | D19: Every Manager sees every Block's Applications (ADR-19); Staff and students cannot review. | E19: Test seed (2 Blocks, 48 students, 7 back-office users); Staff signed in | F19: Passed | G19: 30/10/2026 | H19: CI (mvn verify)

Sheet F-07
A2: Feature | B2: F-07 Balance, forfeit and door code release | R2: Passed
A3: Test requirement | B3: Balance, forfeit and door code release (FR-ASG-04, 11, FR-INV-04); actors: Student, Staff, System | R3: Failed
A4: Number of TCs | B4: =COUNTA(A12:A1000) -> 5 | R4: Pending
A5: Testing Round | B5: Passed | C5: Failed | D5: Pending | E5: N/A | R5: N/A
A6: Round 1 | B6: =COUNTIF($F10:$F998,B5) -> 5 | C6: =COUNTIF($F10:$F998,C5) -> 0 | D6: =COUNTIF($F10:$F998,D5) -> 0 | E6: =COUNTIF($F10:$F998,E5) -> 0
A7: Round 2 | B7: 0 | C7: 0 | D7: 0 | E7: 0
A8: Round 3 | B8: 0 | C8: 0 | D8: 0 | E8: 0
A10: Test Case ID | B10: Test Case Description | C10: Test Case Procedure | D10: Expected Results | E10: Pre-conditions | F10: Round 1 | G10: Test date | H10: Tester | I10: Round 2 | J10: Test date | K10: Tester | L10: Round 3 | M10: Test date | N10: Tester | O10: Note
A11: FR-ASG-04, 11, FR-INV-04
A12: TC-F07-01 | B12: [Main] Assigned and unpaid (yellow); paid but before the check-in start, then without a Room code, the student waits (no code); Staff confirm the Room's code and it is released: the student is a resident (orange), is told and sees the code; a student who pays later receives the current code at once. | C12: Automated (ResidenceIT.doorCodeIsReleasedToPaidResidents): GET /api/inventory/rooms; GET /api/students/me/allocation; GET /api/students/me/door-code; check the answer and the database | D12: Assigned and unpaid (yellow); paid but before the check-in start, then without a Room code, the student waits (no code); Staff confirm the Room's code and it is released: the student is a resident (orange), is told and sees the code; a student who pays later receives the current code at once. | E12: Test seed (2 Blocks, 48 students, 7 back-office users); Student signed in | F12: Passed | G12: 30/10/2026 | H12: CI (mvn verify)
A13: TC-F07-02 | B13: [Main] Staff draw a random code, read it to set the lock, confirm it, and it becomes the Room's code; the database holds it encrypted and every view is in the Audit Log. | C13: Automated (DoorCodeIT.proposesConfirmsAndReveals): GET /api/door-codes; POST /api/door-codes/{room}; POST /api/door-codes/{room}/confirm; POST /api/door-codes/{room}/reveal; check the answer and the database | D13: Staff draw a random code, read it to set the lock, confirm it, and it becomes the Room's code; the database holds it encrypted and every view is in the Audit Log. | E13: Test seed (2 Blocks, 48 students, 7 back-office users); Staff signed in | F13: Passed | G13: 30/10/2026 | H13: CI (mvn verify)
A14: TC-F07-03 | B14: [Main] A student whose Balance is paid and whose check-in start has come waits for the Room's code; once Staff confirm it, it is released to them (spec §6.8): they are told (never the code), see it and become a resident; without a Bed there is nothing to show. | C14: Automated (DoorCodeIT.showsTheStudentTheirCode): GET /api/students/me/door-code; POST /api/students/me/door-code/reveal; GET /api/students/me/furniture; check the answer and the database | D14: A student whose Balance is paid and whose check-in start has come waits for the Room's code; once Staff confirm it, it is released to them (spec §6.8): they are told (never the code), see it and become a resident; without a Bed there is nothing to show. | E14: Test seed (2 Blocks, 48 students, 7 back-office users); Student signed in | F14: Passed | G14: 30/10/2026 | H14: CI (mvn verify)
A15: TC-F07-04 | B15: [Rule] A Balance past its deadline without a claim is forfeited: the Allocation is cancelled, the Balance void, the Application Forfeited, the Deposit kept by the rule "Balance not paid" (a 0 % rule records no refund; a 10 % rule one refund, never two) and the student told; a claim waiting keeps the Bed, and so does a later Balance deadline a Manager chose when approving a late check-in, which may not pass the arrival day (the Balance is paid before check-in). | C15: Automated (ResidenceIT.unpaidBalanceIsForfeited): GET /api/inventory/rooms; POST /api/late-check-ins/{id}/decision; POST /api/students/me/late-check-in; check the answer and the database | D15: A Balance past its deadline without a claim is forfeited: the Allocation is cancelled, the Balance void, the Application Forfeited, the Deposit kept by the rule "Balance not paid" (a 0 % rule records no refund; a 10 % rule one refund, never two) and the student told; a claim waiting keeps the Bed, and so does a later Balance deadline a Manager chose when approving a late check-in, which may not pass the arrival day (the Balance is paid before check-in). | E15: Test seed (2 Blocks, 48 students, 7 back-office users); System (job) signed in | F15: Passed | G15: 30/10/2026 | H15: CI (mvn verify)
A16: TC-F07-05 | B16: [Exception] Codes are 6 new digits; other Blocks and other roles are refused. | C16: Automated (DoorCodeIT.refusesWrongCodes): GET /api/door-codes; POST /api/door-codes/{room}; POST /api/door-codes/{room}/confirm; POST /api/door-codes/{room}/cancel; check the answer and the database | D16: Codes are 6 new digits; other Blocks and other roles are refused. | E16: Test seed (2 Blocks, 48 students, 7 back-office users); Staff signed in | F16: Passed | G16: 30/10/2026 | H16: CI (mvn verify)

Sheet F-08
A2: Feature | B2: F-08 Check-in and check-out desk | R2: Passed
A3: Test requirement | B3: Check-in and check-out desk (FR-ASG-04, 06); actors: Staff | R3: Failed
A4: Number of TCs | B4: =COUNTA(A12:A1000) -> 5 | R4: Pending
A5: Testing Round | B5: Passed | C5: Failed | D5: Pending | E5: N/A | R5: N/A
A6: Round 1 | B6: =COUNTIF($F10:$F998,B5) -> 5 | C6: =COUNTIF($F10:$F998,C5) -> 0 | D6: =COUNTIF($F10:$F998,D5) -> 0 | E6: =COUNTIF($F10:$F998,E5) -> 0
A7: Round 2 | B7: 0 | C7: 0 | D7: 0 | E7: 0
A8: Round 3 | B8: 0 | C8: 0 | D8: 0 | E8: 0
A10: Test Case ID | B10: Test Case Description | C10: Test Case Procedure | D10: Expected Results | E10: Pre-conditions | F10: Round 1 | G10: Test date | H10: Tester | I10: Round 2 | J10: Test date | K10: Tester | L10: Round 3 | M10: Test date | N10: Tester | O10: Note
A11: FR-ASG-04, 06
A12: TC-F08-01 | B12: [Main] The Balance includes the Utility Deposit; until it is paid the desk blocks check-in; then the student checks in with the hand-over items, once only. | C12: Automated (DeskIT.checkInNeedsBalanceAndUtilityDeposit): POST /api/check-in; GET /api/check-in/lookup; GET /api/check-in/today; check the answer and the database | D12: The Balance includes the Utility Deposit; until it is paid the desk blocks check-in; then the student checks in with the hand-over items, once only. | E12: Test seed (2 Blocks, 48 students, 7 back-office users); Staff signed in | F12: Passed | G12: 30/10/2026 | H12: CI (mvn verify)
A13: TC-F08-02 | B13: [Main] Check-out settles the Utility Deposit: the share since the Room's last reading, the damage charge, the refund to the Manager; the Bed is free again, the figures stay as settled and the Room's door code must change. | C13: Automated (DeskIT.checkOutSettlesTheDeposit): GET /api/check-out; GET /api/check-out/{allocationId}; POST /api/check-out/{allocationId}; check the answer and the database | D13: Check-out settles the Utility Deposit: the share since the Room's last reading, the damage charge, the refund to the Manager; the Bed is free again, the figures stay as settled and the Room's door code must change. | E13: Test seed (2 Blocks, 48 students, 7 back-office users); Staff signed in | F13: Passed | G13: 30/10/2026 | H13: CI (mvn verify)
A14: TC-F08-03 | B14: [Main] The desk enters the final meter readings Room by Room, typed or from the XLSX template, before the leavers come: each Room's reading goes to the check-out drafts of its leavers; a Room without leavers in the user's Blocks or a reading below the Room's last one is reported and not saved. | C14: Automated (DeskIT.finalReadingsRoomByRoom): GET /api/check-out/readings; PUT /api/check-out/readings; GET /api/check-out/readings/template; check the answer and the database | D14: The desk enters the final meter readings Room by Room, typed or from the XLSX template, before the leavers come: each Room's reading goes to the check-out drafts of its leavers; a Room without leavers in the user's Blocks or a reading below the Room's last one is reported and not saved. | E14: Test seed (2 Blocks, 48 students, 7 back-office users); Staff signed in | F14: Passed | G14: 30/10/2026 | H14: CI (mvn verify)
A15: TC-F08-04 | B15: [Rule] Check-out records the damage of each furniture item of the Room (spec §6.16): the damage charge is their sum, a damaged item becomes Broken with the reason in its history, an item of another Room is refused; the list shows the Term's check-out date and whether a leaver is past it. | C15: Automated (DeskIT.checkOutRecordsDamagePerItem): run the scenario and check the result | D15: Check-out records the damage of each furniture item of the Room (spec §6.16): the damage charge is their sum, a damaged item becomes Broken with the reason in its history, an item of another Room is refused; the list shows the Term's check-out date and whether a leaver is past it. | E15: Test seed (2 Blocks, 48 students, 7 back-office users); Staff signed in | F15: Passed | G15: 30/10/2026 | H15: CI (mvn verify)
A16: TC-F08-05 | B16: [Exception] Another Block's Staff do not find the student, every Manager does (ADR-19); students and the Admin have no desk. | C16: Automated (DeskIT.deskIsScoped): GET /api/check-in/lookup; GET /api/check-in/today; GET /api/check-out; GET /api/check-out/{allocationId}; check the answer and the database | D16: Another Block's Staff do not find the student, every Manager does (ADR-19); students and the Admin have no desk. | E16: Test seed (2 Blocks, 48 students, 7 back-office users); Staff signed in | F16: Passed | G16: 30/10/2026 | H16: CI (mvn verify)

Sheet F-09
A2: Feature | B2: F-09 Late check-in | R2: Passed
A3: Test requirement | B3: Late check-in (FR-ASG-05); actors: Student, Staff, Manager | R3: Failed
A4: Number of TCs | B4: =COUNTA(A12:A1000) -> 3 | R4: Pending
A5: Testing Round | B5: Passed | C5: Failed | D5: Pending | E5: N/A | R5: N/A
A6: Round 1 | B6: =COUNTIF($F10:$F998,B5) -> 3 | C6: =COUNTIF($F10:$F998,C5) -> 0 | D6: =COUNTIF($F10:$F998,D5) -> 0 | E6: =COUNTIF($F10:$F998,E5) -> 0
A7: Round 2 | B7: 0 | C7: 0 | D7: 0 | E7: 0
A8: Round 3 | B8: 0 | C8: 0 | D8: 0 | E8: 0
A10: Test Case ID | B10: Test Case Description | C10: Test Case Procedure | D10: Expected Results | E10: Pre-conditions | F10: Round 1 | G10: Test date | H10: Tester | I10: Round 2 | J10: Test date | K10: Tester | L10: Round 3 | M10: Test date | N10: Tester | O10: Note
A11: FR-ASG-05
A12: TC-F09-01 | B12: [Main] The student asks online with a reason, the day and an evidence file, up to the check-in end plus late_check_in.max_days; the Managers are told; one request per Term, also after the decision; a Manager approves at most that day. | C12: Automated (LateCheckInIT.studentAsksOnline): GET /api/late-check-ins; POST /api/late-check-ins/{id}/decision; GET /api/students/me/late-check-in; POST /api/students/me/late-check-in; check the answer and the database | D12: The student asks online with a reason, the day and an evidence file, up to the check-in end plus late_check_in.max_days; the Managers are told; one request per Term, also after the decision; a Manager approves at most that day. | E12: Test seed (2 Blocks, 48 students, 7 back-office users); Student signed in | F12: Passed | G12: 30/10/2026 | H12: CI (mvn verify)
A13: TC-F09-02 | B13: [Main] Staff record the request with evidence; the Block Manager approves a deadline, after which the desk lets the student check in even though the Term's window is closed. | C13: Automated (LateCheckInIT.approvedLateCheckIn): GET /api/late-check-ins; POST /api/late-check-ins; POST /api/late-check-ins/{id}/decision; check the answer and the database | D13: Staff record the request with evidence; the Block Manager approves a deadline, after which the desk lets the student check in even though the Term's window is closed. | E13: Test seed (2 Blocks, 48 students, 7 back-office users); Staff signed in | F13: Passed | G13: 30/10/2026 | H13: CI (mvn verify)
A14: TC-F09-03 | B14: [Rule] A rejection needs a reason; every Manager sees the request (ADR-19); a student has one late check-in per Term, so the desk cannot record another after the rejection. | C14: Automated (LateCheckInIT.rejectedLateCheckIn): GET /api/late-check-ins; POST /api/late-check-ins/{id}/decision; check the answer and the database | D14: A rejection needs a reason; every Manager sees the request (ADR-19); a student has one late check-in per Term, so the desk cannot record another after the rejection. | E14: Test seed (2 Blocks, 48 students, 7 back-office users); Manager signed in | F14: Passed | G14: 30/10/2026 | H14: CI (mvn verify)

Sheet F-10
A2: Feature | B2: F-10 Next-Term requests | R2: Passed
A3: Test requirement | B3: Next-Term requests (FR-REQ-01..05); actors: Student, Staff | R3: Failed
A4: Number of TCs | B4: =COUNTA(A12:A1000) -> 6 | R4: Pending
A5: Testing Round | B5: Passed | C5: Failed | D5: Pending | E5: N/A | R5: N/A
A6: Round 1 | B6: =COUNTIF($F10:$F998,B5) -> 6 | C6: =COUNTIF($F10:$F998,C5) -> 0 | D6: =COUNTIF($F10:$F998,D5) -> 0 | E6: =COUNTIF($F10:$F998,E5) -> 0
A7: Round 2 | B7: 0 | C7: 0 | D7: 0 | E7: 0
A8: Round 3 | B8: 0 | C8: 0 | D8: 0 | E8: 0
A10: Test Case ID | B10: Test Case Description | C10: Test Case Procedure | D10: Expected Results | E10: Pre-conditions | F10: Round 1 | G10: Test date | H10: Tester | I10: Round 2 | J10: Test date | K10: Tester | L10: Round 3 | M10: Test date | N10: Tester | O10: Note
A11: FR-REQ-01..05
A12: TC-F10-01 | B12: [Main] Staff of the Block approve with a free matching Bed of the next Term: the next-Term Allocation moves there (the student still lives in their Room this Term) and the next-Term fee will be that Bed's price; no Invoice or refund is made; Staff of another Block see nothing; after the next-Term fees the Beds are fixed. | C12: Automated (RoomChangeIT.staffApprove): GET /api/room-changes; POST /api/room-changes/{id}/decision; GET /api/room-changes/{id}/matching-beds; check the answer and the database | D12: Staff of the Block approve with a free matching Bed of the next Term: the next-Term Allocation moves there (the student still lives in their Room this Term) and the next-Term fee will be that Bed's price; no Invoice or refund is made; Staff of another Block see nothing; after the next-Term fees the Beds are fixed. | E12: Test seed (2 Blocks, 48 students, 7 back-office users); Staff signed in | F12: Passed | G12: 30/10/2026 | H12: CI (mvn verify)
A13: TC-F10-02 | B13: [Main] A direct swap of next-Term Beds: the partner accepts, Staff check and approve, the two next-Term Allocations exchange Beds while both students stay where they live this Term. | C13: Automated (SwapIT.directSwap): GET /api/students/me/requests; GET /api/swap-invitations/{id}; POST /api/swap-invitations/{id}/respond; GET /api/swaps; check the answer and the database | D13: A direct swap of next-Term Beds: the partner accepts, Staff check and approve, the two next-Term Allocations exchange Beds while both students stay where they live this Term. | E13: Test seed (2 Blocks, 48 students, 7 back-office users); Student signed in | F13: Passed | G13: 30/10/2026 | H13: CI (mvn verify)
A14: TC-F10-03 | B14: [Main] The requests window in one list (room changes, swaps, Room Class changes, extensions), oldest first; a bulk decision decides each one in its own transaction and reports those it could not (a change still waiting for consent); a bulk rejection needs a reason; Staff of another Block see nothing. | C14: Automated (NextTermRequestIT.windowListAndBulk): GET /api/renewals/overview; POST /api/room-class-changes; POST /api/students/me/stay/extension; GET /api/next-term-requests; check the answer and the database | D14: The requests window in one list (room changes, swaps, Room Class changes, extensions), oldest first; a bulk decision decides each one in its own transaction and reports those it could not (a change still waiting for consent); a bulk rejection needs a reason; Staff of another Block see nothing. | E14: Test seed (2 Blocks, 48 students, 7 back-office users); Staff signed in | F14: Passed | G14: 30/10/2026 | H14: CI (mvn verify)
A15: TC-F10-04 | B15: [Rule] A Room Class change of a Room for the next Term: every other continuing resident must agree (one in the Stay's last Term is not asked); Staff cannot approve before; the furniture check reserves the missing items of the Block store; the Room's class changes for the next Term only, and the next-Term price follows it; a refusal cancels a change; Staff of another Block see nothing. | C15: Automated (NextTermRequestIT.roomClassChange): GET /api/students/me/requests; GET /api/room-class-changes/options; POST /api/room-class-changes; POST /api/room-class-changes/{id}/consent; check the answer and the database | D15: A Room Class change of a Room for the next Term: every other continuing resident must agree (one in the Stay's last Term is not asked); Staff cannot approve before; the furniture check reserves the missing items of the Block store; the Room's class changes for the next Term only, and the next-Term price follows it; a refusal cancels a change; Staff of another Block see nothing. | E15: Test seed (2 Blocks, 48 students, 7 back-office users); Student signed in | F15: Passed | G15: 30/10/2026 | H15: CI (mvn verify)
A16: TC-F10-05 | B16: [Rule] An extension in the Stay's last Term is approved at once (the Bed is kept, the Stay commits more Terms); with an overdue Invoice it waits for Staff, who decide it with a note to reject; the length is checked; the end of the stay releases the next-Term Bed at once; after the request deadline nothing can be filed. | C16: Automated (NextTermRequestIT.extensionsAndEndOfStay): GET /api/students/me/allocation; POST /api/students/me/stay/extension; POST /api/students/me/stay/end; GET /api/stay-requests; check the answer and the database | D16: An extension in the Stay's last Term is approved at once (the Bed is kept, the Stay commits more Terms); with an overdue Invoice it waits for Staff, who decide it with a note to reject; the length is checked; the end of the stay releases the next-Term Bed at once; after the request deadline nothing can be filed. | E16: Test seed (2 Blocks, 48 students, 7 back-office users); Student signed in | F16: Passed | G16: 30/10/2026 | H16: CI (mvn verify)
A17: TC-F10-06 | B17: [Exception] A rejection needs a listed reason; the student sees it; students may not decide. | C17: Automated (RoomChangeIT.staffReject): GET /api/room-changes; POST /api/room-changes/{id}/decision; check the answer and the database | D17: A rejection needs a listed reason; the student sees it; students may not decide. | E17: Test seed (2 Blocks, 48 students, 7 back-office users); Staff signed in | F17: Passed | G17: 30/10/2026 | H17: CI (mvn verify)

Sheet F-11
A2: Feature | B2: F-11 Requests window, reconciliation and next-Term fees | R2: Passed
A3: Test requirement | B3: Requests window, reconciliation and next-Term fees (FR-ASG-07, 08, FR-AUTH-08); actors: Manager, System | R3: Failed
A4: Number of TCs | B4: =COUNTA(A12:A1000) -> 6 | R4: Pending
A5: Testing Round | B5: Passed | C5: Failed | D5: Pending | E5: N/A | R5: N/A
A6: Round 1 | B6: =COUNTIF($F10:$F998,B5) -> 6 | C6: =COUNTIF($F10:$F998,C5) -> 0 | D6: =COUNTIF($F10:$F998,D5) -> 0 | E6: =COUNTIF($F10:$F998,E5) -> 0
A7: Round 2 | B7: 0 | C7: 0 | D7: 0 | E7: 0
A8: Round 3 | B8: 0 | C8: 0 | D8: 0 | E8: 0
A10: Test Case ID | B10: Test Case Description | C10: Test Case Procedure | D10: Expected Results | E10: Pre-conditions | F10: Round 1 | G10: Test date | H10: Tester | I10: Round 2 | J10: Test date | K10: Tester | L10: Round 3 | M10: Test date | N10: Tester | O10: Note
A11: FR-ASG-07, 08, FR-AUTH-08
A12: TC-F11-01 | B12: [Main] M2 opens the requests window once: a resident with Terms left keeps the Bed as continuing, one in the Stay's last Term as awaiting extension; a student not living in the Room yet and a terminated resident get none. My Room shows the next Term with its price, the students are told, Staff and Managers read the overview, and the new students' assignment of the next Term waits for the request deadline. | C12: Automated (RenewalIT.windowOpens): GET /api/inventory/rooms; GET /api/students/me/allocation; GET /api/renewals; GET /api/renewals/overview; check the answer and the database | D12: M2 opens the requests window once: a resident with Terms left keeps the Bed as continuing, one in the Stay's last Term as awaiting extension; a student not living in the Room yet and a terminated resident get none. My Room shows the next Term with its price, the students are told, Staff and Managers read the overview, and the new students' assignment of the next Term waits for the request deadline. | E12: Test seed (2 Blocks, 48 students, 7 back-office users); System (job) signed in | F12: Passed | G12: 30/10/2026 | H12: CI (mvn verify)
A13: TC-F11-02 | B13: [Main] M3 closes filing: a Bed still awaiting extension is released (the student is told in-app and by email, with the day to check out), a continuing one stays; the overview counts the ending. | C13: Automated (RenewalIT.notExtendedAtTheDeadline): GET /api/students/me/allocation; GET /api/renewals/overview; check the answer and the database | D13: M3 closes filing: a Bed still awaiting extension is released (the student is told in-app and by email, with the day to check out), a continuing one stays; the overview counts the ending. | E13: Test seed (2 Blocks, 48 students, 7 back-office users); System (job) signed in | F13: Passed | G13: 30/10/2026 | H13: CI (mvn verify)
A14: TC-F11-03 | B14: [Main] The enrolled list of the next Term: a continuing resident who graduated (group 1, the directory updated: group 4), a continuing resident missing from the list (group 2), an unknown code (group 3), another student's changed status (group 4); the template; Managers upload, the Admin reads, Staff may not; a file without a student code column is refused. | C14: Automated (ReconciliationIT.enrolledListGroups): GET /api/reconciliations; GET /api/reconciliations/template; POST /api/reconciliations; GET /api/reconciliations/{id}; check the answer and the database | D14: The enrolled list of the next Term: a continuing resident who graduated (group 1, the directory updated: group 4), a continuing resident missing from the list (group 2), an unknown code (group 3), another student's changed status (group 4); the template; Managers upload, the Admin reads, Staff may not; a file without a student code column is refused. | E14: Test seed (2 Blocks, 48 students, 7 back-office users); Manager signed in | F14: Passed | G14: 30/10/2026 | H14: CI (mvn verify)
A15: TC-F11-04 | B15: [Rule] Resolving: a note is required; "Not enrolled" releases the student's Bed for the next Term (told in the app); "Enrolled" keeps everything; an item is resolved once; then nothing blocks the next-Term fees. | C15: Automated (ReconciliationIT.resolveItems): GET /api/next-term-fees; GET /api/reconciliations; POST /api/reconciliations; GET /api/reconciliations/{id}; check the answer and the database | D15: Resolving: a note is required; "Not enrolled" releases the student's Bed for the next Term (told in the app); "Enrolled" keeps everything; an item is resolved once; then nothing blocks the next-Term fees. | E15: Test seed (2 Blocks, 48 students, 7 back-office users); Manager signed in | F15: Passed | G15: 30/10/2026 | H15: CI (mvn verify)
A16: TC-F11-05 | B16: [Rule] Issue next-Term fees: the preview names what blocks them (filing still open, no reconciliation); once filing closed and the enrolled list is reconciled a Manager issues one fee per continuing resident = 100 % of the next Term's price of the Bed (no Deposit); issuing again charges nobody twice; leavers receive the end-of-stay notice; Staff may not issue; the fee cannot be claimed while Utility is overdue; paid, the Stay counts the next Term. | C16: Automated (RenewalIT.nextTermFees): GET /api/students/me/allocation; GET /api/next-term-fees; POST /api/next-term-fees/issue; check the answer and the database | D16: Issue next-Term fees: the preview names what blocks them (filing still open, no reconciliation); once filing closed and the enrolled list is reconciled a Manager issues one fee per continuing resident = 100 % of the next Term's price of the Bed (no Deposit); issuing again charges nobody twice; leavers receive the end-of-stay notice; Staff may not issue; the fee cannot be claimed while Utility is overdue; paid, the Stay counts the next Term. | E16: Test seed (2 Blocks, 48 students, 7 back-office users); Manager signed in | F16: Passed | G16: 30/10/2026 | H16: CI (mvn verify)
A17: TC-F11-06 | B17: [Exception] M7: a next-Term fee unpaid at its deadline with no claim waiting is void and its Bed released (nothing kept); a fee whose claim waits for a Manager keeps the Bed. | C17: Automated (RenewalIT.unpaidFeesReleaseTheBed): GET /api/students/me/allocation; POST /api/next-term-fees/issue; check the answer and the database | D17: M7: a next-Term fee unpaid at its deadline with no claim waiting is void and its Bed released (nothing kept); a fee whose claim waits for a Manager keeps the Bed. | E17: Test seed (2 Blocks, 48 students, 7 back-office users); System (job) signed in | F17: Passed | G17: 30/10/2026 | H17: CI (mvn verify)

Sheet F-12
A2: Feature | B2: F-12 Turnover and operational moves | R2: Passed
A3: Test requirement | B3: Turnover and operational moves (FR-ASG-10); actors: Staff, Manager | R3: Failed
A4: Number of TCs | B4: =COUNTA(A12:A1000) -> 3 | R4: Pending
A5: Testing Round | B5: Passed | C5: Failed | D5: Pending | E5: N/A | R5: N/A
A6: Round 1 | B6: =COUNTIF($F10:$F998,B5) -> 3 | C6: =COUNTIF($F10:$F998,C5) -> 0 | D6: =COUNTIF($F10:$F998,D5) -> 0 | E6: =COUNTIF($F10:$F998,E5) -> 0
A7: Round 2 | B7: 0 | C7: 0 | D7: 0 | E7: 0
A8: Round 3 | B8: 0 | C8: 0 | D8: 0 | E8: 0
A10: Test Case ID | B10: Test Case Description | C10: Test Case Procedure | D10: Expected Results | E10: Pre-conditions | F10: Round 1 | G10: Test date | H10: Tester | I10: Round 2 | J10: Test date | K10: Tester | L10: Round 3 | M10: Test date | N10: Tester | O10: Note
A11: FR-ASG-10
A12: TC-F12-01 | B12: [Main] The turnover: from the next Term's check-in start a paid continuing resident receives the Room's code and lives in the next Term (the current Term's Allocation ends); a mover's old Room needs a new code; the turnover list shows leavers, movers and the Rooms whose residents change, and Staff record their meter readings. | C12: Automated (RenewalIT.turnover): GET /api/students/me/allocation; POST /api/next-term-fees/issue; GET /api/turnover; POST /api/turnover/meter-cuts; check the answer and the database | D12: The turnover: from the next Term's check-in start a paid continuing resident receives the Room's code and lives in the next Term (the current Term's Allocation ends); a mover's old Room needs a new code; the turnover list shows leavers, movers and the Rooms whose residents change, and Staff record their meter readings. | E12: Test seed (2 Blocks, 48 students, 7 back-office users); Staff signed in | F12: Passed | G12: 30/10/2026 | H12: CI (mvn verify)
A13: TC-F12-02 | B13: [Main] Staff move a resident to another Room of their Block for a reason: both meters are read, the old Room's code must change, the next-Term Bed follows, nothing is charged; the student is told; the moves list shows it; validation, other Blocks and students are refused. | C13: Automated (OperationalMoveIT.staffMoveAResident): GET /api/operational-moves/options; POST /api/operational-moves; GET /api/operational-moves; check the answer and the database | D13: Staff move a resident to another Room of their Block for a reason: both meters are read, the old Room's code must change, the next-Term Bed follows, nothing is charged; the student is told; the moves list shows it; validation, other Blocks and students are refused. | E13: Test seed (2 Blocks, 48 students, 7 back-office users); Staff signed in | F13: Passed | G13: 30/10/2026 | H13: CI (mvn verify)
A14: TC-F12-03 | B14: [Exception] After the next-Term fees are issued, Staff may no longer move a next-Term Bed; a Manager moves an unpaid one and its fee is void and issued again for the new Bed; a paid fee allows only a Bed of the same price. | C14: Automated (OperationalMoveIT.frozenAfterTheFees): POST /api/next-term-fees/issue; POST /api/operational-moves; check the answer and the database | D14: After the next-Term fees are issued, Staff may no longer move a next-Term Bed; a Manager moves an unpaid one and its fee is void and issued again for the new Bed; a paid fee allows only a Bed of the same price. | E14: Test seed (2 Blocks, 48 students, 7 back-office users); Staff signed in | F14: Passed | G14: 30/10/2026 | H14: CI (mvn verify)

Sheet F-13
A2: Feature | B2: F-13 Maintenance with routing, time limits and escalation | R2: Passed
A3: Test requirement | B3: Maintenance with routing, time limits and escalation (FR-MNT-01, 02, FR-REQ-06, 07); actors: Student, Staff, Manager | R3: Failed
A4: Number of TCs | B4: =COUNTA(A12:A1000) -> 7 | R4: Pending
A5: Testing Round | B5: Passed | C5: Failed | D5: Pending | E5: N/A | R5: N/A
A6: Round 1 | B6: =COUNTIF($F10:$F998,B5) -> 7 | C6: =COUNTIF($F10:$F998,C5) -> 0 | D6: =COUNTIF($F10:$F998,D5) -> 0 | E6: =COUNTIF($F10:$F998,E5) -> 0
A7: Round 2 | B7: 0 | C7: 0 | D7: 0 | E7: 0
A8: Round 3 | B8: 0 | C8: 0 | D8: 0 | E8: 0
A10: Test Case ID | B10: Test Case Description | C10: Test Case Procedure | D10: Expected Results | E10: Pre-conditions | F10: Round 1 | G10: Test date | H10: Tester | I10: Round 2 | J10: Test date | K10: Tester | L10: Round 3 | M10: Test date | N10: Tester | O10: Note
A11: FR-MNT-01, 02, FR-REQ-06, 07
A12: TC-F13-01 | B12: [Main] A checked-in student reports with photos and follows the request; the form is validated. | C12: Automated (MaintenanceIT.studentReportsAndFollows): POST /api/maintenance-requests; GET /api/maintenance-requests/options; GET /api/maintenance-requests/{id}; GET /api/students/me/requests; check the answer and the database | D12: A checked-in student reports with photos and follows the request; the form is validated. | E12: Test seed (2 Blocks, 48 students, 7 back-office users); Student signed in | F12: Passed | G12: 30/10/2026 | H12: CI (mvn verify)
A13: TC-F13-02 | B13: [Main] Staff of the Block assign, plan the visit, post updates and resolve; the student is notified, reopens once and confirms the fix. Photos open through signed links. | C13: Automated (MaintenanceIT.staffWorkTheRequest): GET /api/maintenance-requests; GET /api/maintenance-requests/options; GET /api/maintenance-requests/{id}; PATCH /api/maintenance-requests/{id}; check the answer and the database | D13: Staff of the Block assign, plan the visit, post updates and resolve; the student is notified, reopens once and confirms the fix. Photos open through signed links. | E13: Test seed (2 Blocks, 48 students, 7 back-office users); Staff signed in | F13: Passed | G13: 30/10/2026 | H13: CI (mvn verify)
A14: TC-F13-03 | B14: [Main] A Staff member reads their own duty, request types and workload, and starts or ends their shift (A-60); the change is audited, and students may not use it. | C14: Automated (BlockStaffIT.staffStartAndEndTheirShift): GET /api/block-staff/me; PUT /api/block-staff/me/duty; check the answer and the database | D14: A Staff member reads their own duty, request types and workload, and starts or ends their shift (A-60); the change is audited, and students may not use it. | E14: Test seed (2 Blocks, 48 students, 7 back-office users); Staff signed in | F14: Passed | G14: 30/10/2026 | H14: CI (mvn verify)
A15: TC-F13-04 | B15: [Rule] A new Maintenance Request gets its SLA deadline from the Block's timer (urgent sooner than normal) and may name a furniture item of the Room, which the queue and the detail show; the item's history keeps the repair, reported and resolved; an item of another Room is refused. | C15: Automated (OperationsIT.slaDeadlineAndFurnitureItem): run the scenario and check the result | D15: A new Maintenance Request gets its SLA deadline from the Block's timer (urgent sooner than normal) and may name a furniture item of the Room, which the queue and the detail show; the item's history keeps the repair, reported and resolved; an item of another Room is refused. | E15: Test seed (2 Blocks, 48 students, 7 back-office users); Student signed in | F15: Passed | G15: 30/10/2026 | H15: CI (mvn verify)
A16: TC-F13-05 | B16: [Rule] Only the person in charge changes the status; another Staff member of the Block takes the request over first (recorded in its history), and a Manager may act on any request. | C16: Automated (MaintenanceIT.personInChargeChangesTheStatus): PATCH /api/maintenance-requests/{id}; check the answer and the database | D16: Only the person in charge changes the status; another Staff member of the Block takes the request over first (recorded in its history), and a Manager may act on any request. | E16: Test seed (2 Blocks, 48 students, 7 back-office users); Staff signed in | F16: Passed | G16: 30/10/2026 | H16: CI (mvn verify)
A17: TC-F13-06 | B17: [Rule] An unassigned request escalates, then passes its timer; the Manager reassigns it once. | C17: Automated (EscalationIT.maintenanceEscalatesAndIsReassigned): GET /api/escalations; POST /api/escalations/{id}/actions; check the answer and the database | D17: An unassigned request escalates, then passes its timer; the Manager reassigns it once. | E17: Test seed (2 Blocks, 48 students, 7 back-office users); Manager signed in | F17: Passed | G17: 30/10/2026 | H17: CI (mvn verify)
A18: TC-F13-07 | B18: [Exception] The queue is scoped: another Block's Staff neither see nor count the request; Managers do (ADR-19). | C18: Automated (MaintenanceIT.queueIsScoped): GET /api/maintenance-requests; check the answer and the database | D18: The queue is scoped: another Block's Staff neither see nor count the request; Managers do (ADR-19). | E18: Test seed (2 Blocks, 48 students, 7 back-office users); Staff signed in | F18: Passed | G18: 30/10/2026 | H18: CI (mvn verify)

Sheet F-14
A2: Feature | B2: F-14 Meter readings and Utility Invoices | R2: Passed
A3: Test requirement | B3: Meter readings and Utility Invoices (FR-BIL-04); actors: Staff | R3: Failed
A4: Number of TCs | B4: =COUNTA(A12:A1000) -> 4 | R4: Pending
A5: Testing Round | B5: Passed | C5: Failed | D5: Pending | E5: N/A | R5: N/A
A6: Round 1 | B6: =COUNTIF($F10:$F998,B5) -> 4 | C6: =COUNTIF($F10:$F998,C5) -> 0 | D6: =COUNTIF($F10:$F998,D5) -> 0 | E6: =COUNTIF($F10:$F998,E5) -> 0
A7: Round 2 | B7: 0 | C7: 0 | D7: 0 | E7: 0
A8: Round 3 | B8: 0 | C8: 0 | D8: 0 | E8: 0
A10: Test Case ID | B10: Test Case Description | C10: Test Case Procedure | D10: Expected Results | E10: Pre-conditions | F10: Round 1 | G10: Test date | H10: Tester | I10: Round 2 | J10: Test date | K10: Tester | L10: Round 3 | M10: Test date | N10: Tester | O10: Note
A11: FR-BIL-04
A12: TC-F14-01 | B12: [Main] Closing the month issues each resident's Utility Invoice with its breakdown; then it is read-only. | C12: Automated (MeterIT.closeIssuesUtilityInvoices): POST /api/meter-periods/{id}/close; PUT /api/meter-periods/{id}/readings/{room}; check the answer and the database | D12: Closing the month issues each resident's Utility Invoice with its breakdown; then it is read-only. | E12: Test seed (2 Blocks, 48 students, 7 back-office users); Staff signed in | F12: Passed | G12: 30/10/2026 | H12: CI (mvn verify)
A13: TC-F14-02 | B13: [Rule] Within a segment, shares follow the time each resident lived in the Room; totals round up. | C13: Automated (UtilitySplitTest.sharesFollowTimeInTheRoom): POST /api/meter-periods/{id}/close; check the answer and the database | D13: Within a segment, shares follow the time each resident lived in the Room; totals round up. | E13: Test seed (2 Blocks, 48 students, 7 back-office users); Staff signed in | F13: Passed | G13: 30/10/2026 | H13: CI (mvn verify)
A14: TC-F14-03 | B14: [Rule] A reading may not go back; an unusual jump waits for a confirmation. | C14: Automated (MeterIT.readingRules): POST /api/meter-periods/{id}/close; GET /api/meter-periods/{id}/readings; GET /api/meter-periods/{id}/readings/{room}; PUT /api/meter-periods/{id}/readings/{room}; check the answer and the database | D14: A reading may not go back; an unusual jump waits for a confirmation. | E14: Test seed (2 Blocks, 48 students, 7 back-office users); Staff signed in | F14: Passed | G14: 30/10/2026 | H14: CI (mvn verify)
A15: TC-F14-04 | B15: [Exception] A CSV import checks every line before it saves any. | C15: Automated (MeterIT.importCsv): POST /api/meter-periods/{id}/import; check the answer and the database | D15: A CSV import checks every line before it saves any. | E15: Test seed (2 Blocks, 48 students, 7 back-office users); Staff signed in | F15: Passed | G15: 30/10/2026 | H15: CI (mvn verify)

Sheet F-15
A2: Feature | B2: F-15 Utility debt and termination | R2: Passed
A3: Test requirement | B3: Utility debt and termination (FR-BIL-05, FR-ASG-09); actors: System, Manager | R3: Failed
A4: Number of TCs | B4: =COUNTA(A12:A1000) -> 4 | R4: Pending
A5: Testing Round | B5: Passed | C5: Failed | D5: Pending | E5: N/A | R5: N/A
A6: Round 1 | B6: =COUNTIF($F10:$F998,B5) -> 4 | C6: =COUNTIF($F10:$F998,C5) -> 0 | D6: =COUNTIF($F10:$F998,D5) -> 0 | E6: =COUNTIF($F10:$F998,E5) -> 0
A7: Round 2 | B7: 0 | C7: 0 | D7: 0 | E7: 0
A8: Round 3 | B8: 0 | C8: 0 | D8: 0 | E8: 0
A10: Test Case ID | B10: Test Case Description | C10: Test Case Procedure | D10: Expected Results | E10: Pre-conditions | F10: Round 1 | G10: Test date | H10: Tester | I10: Round 2 | J10: Test date | K10: Tester | L10: Round 3 | M10: Test date | N10: Tester | O10: Note
A11: FR-BIL-05, FR-ASG-09
A12: TC-F15-01 | B12: [Main] An overdue Utility Invoice gives warning 1 (in-app and email), once; a second overdue month gives the final warning with the termination day (today + 3); paying everything closes both. | C12: Automated (UtilityDebtIT.warningsThenPaidInFull): GET /api/students/me/invoices; check the answer and the database | D12: An overdue Utility Invoice gives warning 1 (in-app and email), once; a second overdue month gives the final warning with the termination day (today + 3); paying everything closes both. | E12: Test seed (2 Blocks, 48 students, 7 back-office users); System (job) signed in | F12: Passed | G12: 30/10/2026 | H12: CI (mvn verify)
A13: TC-F15-02 | B13: [Main] A Manager terminates a resident's stay with a reason: Notice sent with the move-out date, the student is told (in-app and email) and sees it on My Room, the desk lists the check-out; Staff read it but may not start or cancel; one termination at a time; a Manager cancels it with a reason and the student is told. | C13: Automated (TerminationIT.managerTerminatesAndCancels): GET /api/students/me/allocation; GET /api/terminations; POST /api/terminations; POST /api/terminations/{id}/cancel; check the answer and the database | D13: A Manager terminates a resident's stay with a reason: Notice sent with the move-out date, the student is told (in-app and email) and sees it on My Room, the desk lists the check-out; Staff read it but may not start or cancel; one termination at a time; a Manager cancels it with a reason and the student is told. | E13: Test seed (2 Blocks, 48 students, 7 back-office users); Manager signed in | F13: Passed | G13: 30/10/2026 | H13: CI (mvn verify)
A14: TC-F15-03 | B14: [Rule] From the termination day, two overdue months terminate the stay (notice to the student, the Managers' list); a debt reaching the Utility Deposit does too, even in its first month; with that rule off one month does not, and nothing happens before the termination day. | C14: Automated (UtilityDebtIT.debtTerminatesTheStay): GET /api/terminations; check the answer and the database | D14: From the termination day, two overdue months terminate the stay (notice to the student, the Managers' list); a debt reaching the Utility Deposit does too, even in its first month; with that rule off one month does not, and nothing happens before the termination day. | E14: Test seed (2 Blocks, 48 students, 7 back-office users); System (job) signed in | F14: Passed | G14: 30/10/2026 | H14: CI (mvn verify)
A15: TC-F15-04 | B15: [Exception] Past the move-out date the termination is Overdue: Managers and the Block's Staff are told, the Room's door code must change and the student no longer sees it; the check-out closes the termination and refunds the unused room fee by its rule (Not enrolled 30 %, decided by a Manager). | C15: Automated (TerminationIT.overdueThenCheckedOut): GET /api/students/me/door-code; GET /api/terminations; POST /api/terminations; check the answer and the database | D15: Past the move-out date the termination is Overdue: Managers and the Block's Staff are told, the Room's door code must change and the student no longer sees it; the check-out closes the termination and refunds the unused room fee by its rule (Not enrolled 30 %, decided by a Manager). | E15: Test seed (2 Blocks, 48 students, 7 back-office users); System (job) signed in | F15: Passed | G15: 30/10/2026 | H15: CI (mvn verify)

Sheet F-16
A2: Feature | B2: F-16 Inventory, Room Class by Term, furniture | R2: Passed
A3: Test requirement | B3: Inventory, Room Class by Term, furniture (FR-INV-01..03); actors: Manager, Staff | R3: Failed
A4: Number of TCs | B4: =COUNTA(A12:A1000) -> 4 | R4: Pending
A5: Testing Round | B5: Passed | C5: Failed | D5: Pending | E5: N/A | R5: N/A
A6: Round 1 | B6: =COUNTIF($F10:$F998,B5) -> 4 | C6: =COUNTIF($F10:$F998,C5) -> 0 | D6: =COUNTIF($F10:$F998,D5) -> 0 | E6: =COUNTIF($F10:$F998,E5) -> 0
A7: Round 2 | B7: 0 | C7: 0 | D7: 0 | E7: 0
A8: Round 3 | B8: 0 | C8: 0 | D8: 0 | E8: 0
A10: Test Case ID | B10: Test Case Description | C10: Test Case Procedure | D10: Expected Results | E10: Pre-conditions | F10: Round 1 | G10: Test date | H10: Tester | I10: Round 2 | J10: Test date | K10: Tester | L10: Round 3 | M10: Test date | N10: Tester | O10: Note
A11: FR-INV-01..03
A12: TC-F16-01 | B12: [Main] A Manager sets Rooms' class for Spring 2027; Fall 2026 keeps the old class, the Rooms and Beds screen and the assignment inputs of Spring 2027 use the new one, conformance shows what the class lacks, and every Room's change is in the Audit Log. | C12: Automated (RoomClassIT.setsClassForTheNextTerm): GET /api/admin/room-classes; GET /api/inventory/rooms; PUT /api/inventory/room-classes; GET /api/inventory/rooms/{code}/details; check the answer and the database | D12: A Manager sets Rooms' class for Spring 2027; Fall 2026 keeps the old class, the Rooms and Beds screen and the assignment inputs of Spring 2027 use the new one, conformance shows what the class lacks, and every Room's change is in the Audit Log. | E12: Test seed (2 Blocks, 48 students, 7 back-office users); Manager signed in | F12: Passed | G12: 30/10/2026 | H12: CI (mvn verify)
A13: TC-F16-02 | B13: [Main] Staff move items inside their Block now (status follows the place, the Room's conformance changes); moving to another Block is a Manager's transfer, planned and then done by Staff; a planned move can also be cancelled. | C13: Automated (FurnitureIT.movesAndTransfersItems): GET /api/inventory/rooms/{code}/details; GET /api/furniture/{id}; GET /api/furniture/moves; POST /api/furniture/moves; check the answer and the database | D13: Staff move items inside their Block now (status follows the place, the Room's conformance changes); moving to another Block is a Manager's transfer, planned and then done by Staff; a planned move can also be cancelled. | E13: Test seed (2 Blocks, 48 students, 7 back-office users); Staff signed in | F13: Passed | G13: 30/10/2026 | H13: CI (mvn verify)
A14: TC-F16-03 | B14: [Rule] A running Term keeps its classes, and a Room whose Beds are already given for the Term (an Allocation) keeps its class there, so no price already charged changes. | C14: Automated (RoomClassIT.keepsClassesWhosePriceIsFixed): GET /api/inventory/room-classes; PUT /api/inventory/room-classes; check the answer and the database | D14: A running Term keeps its classes, and a Room whose Beds are already given for the Term (an Allocation) keeps its class there, so no price already charged changes. | E14: Test seed (2 Blocks, 48 students, 7 back-office users); Manager signed in | F14: Passed | G14: 30/10/2026 | H14: CI (mvn verify)
A15: TC-F16-04 | B15: [Exception] Only Managers set classes; students cannot read; bad input is named. | C15: Automated (RoomClassIT.refusesWrongRequests): GET /api/inventory/room-classes; PUT /api/inventory/room-classes; check the answer and the database | D15: Only Managers set classes; students cannot read; bad input is named. | E15: Test seed (2 Blocks, 48 students, 7 back-office users); Student signed in | F15: Passed | G15: 30/10/2026 | H15: CI (mvn verify)

Sheet F-17
A2: Feature | B2: F-17 Notifications, announcements and push | R2: Passed
A3: Test requirement | B3: Notifications, announcements and push (FR-NTF-01..03); actors: All | R3: Failed
A4: Number of TCs | B4: =COUNTA(A12:A1000) -> 4 | R4: Pending
A5: Testing Round | B5: Passed | C5: Failed | D5: Pending | E5: N/A | R5: N/A
A6: Round 1 | B6: =COUNTIF($F10:$F998,B5) -> 4 | C6: =COUNTIF($F10:$F998,C5) -> 0 | D6: =COUNTIF($F10:$F998,D5) -> 0 | E6: =COUNTIF($F10:$F998,E5) -> 0
A7: Round 2 | B7: 0 | C7: 0 | D7: 0 | E7: 0
A8: Round 3 | B8: 0 | C8: 0 | D8: 0 | E8: 0
A10: Test Case ID | B10: Test Case Description | C10: Test Case Procedure | D10: Expected Results | E10: Pre-conditions | F10: Round 1 | G10: Test date | H10: Tester | I10: Round 2 | J10: Test date | K10: Tester | L10: Round 3 | M10: Test date | N10: Tester | O10: Note
A11: FR-NTF-01..03
A12: TC-F17-01 | B12: [Main] The Admin writes a pinned announcement for all students; a student reads it at the top of the board and in the bell, unread; marking it read in the bell (id `ann-…`) updates both; the Admin sees one read. | C12: Automated (AnnouncementIT.adminAnnouncesToEveryStudent): GET /api/notifications; POST /api/notifications/{id}/read; GET /api/students/me/board; GET /api/announcements; check the answer and the database | D12: The Admin writes a pinned announcement for all students; a student reads it at the top of the board and in the bell, unread; marking it read in the bell (id `ann-…`) updates both; the Admin sees one read. | E12: Test seed (2 Blocks, 48 students, 7 back-office users); Admin signed in | F12: Passed | G12: 30/10/2026 | H12: CI (mvn verify)
A13: TC-F17-02 | B13: [Main] A notification is pushed to the user's devices after commit; an expired token is disabled. | C13: Automated (DevicesIT.pushAfterCommit): POST /api/devices; check the answer and the database | D13: A notification is pushed to the user's devices after commit; an expired token is disabled. | E13: Test seed (2 Blocks, 48 students, 7 back-office users); System (job) signed in | F13: Passed | G13: 30/10/2026 | H13: CI (mvn verify)
A14: TC-F17-03 | B14: [Exception] Staff write only to the residents of their Blocks: everybody or another Block is refused; the residents of the Block read it and other students do not; Staff end their own announcement; students cannot write one. | C14: Automated (AnnouncementIT.staffAnnounceToTheirBlocks): GET /api/students/me/board; GET /api/announcements; GET /api/announcements/options; POST /api/announcements; check the answer and the database | D14: Staff write only to the residents of their Blocks: everybody or another Block is refused; the residents of the Block read it and other students do not; Staff end their own announcement; students cannot write one. | E14: Test seed (2 Blocks, 48 students, 7 back-office users); Staff signed in | F14: Passed | G14: 30/10/2026 | H14: CI (mvn verify)
A15: TC-F17-04 | B15: [Exception] Signed-in users only. | C15: Automated (NotificationsIT.requiresSignIn): GET /api/notifications; check the answer and the database | D15: Signed-in users only. | E15: Test seed (2 Blocks, 48 students, 7 back-office users); Student signed in | F15: Passed | G15: 30/10/2026 | H15: CI (mvn verify)

Sheet F-18
A2: Feature | B2: F-18 Dashboards, reports, exports and search | R2: Passed
A3: Test requirement | B3: Dashboards, reports, exports and search (FR-RPT-01..04); actors: Staff, Manager, Admin | R3: Failed
A4: Number of TCs | B4: =COUNTA(A12:A1000) -> 5 | R4: Pending
A5: Testing Round | B5: Passed | C5: Failed | D5: Pending | E5: N/A | R5: N/A
A6: Round 1 | B6: =COUNTIF($F10:$F998,B5) -> 5 | C6: =COUNTIF($F10:$F998,C5) -> 0 | D6: =COUNTIF($F10:$F998,D5) -> 0 | E6: =COUNTIF($F10:$F998,E5) -> 0
A7: Round 2 | B7: 0 | C7: 0 | D7: 0 | E7: 0
A8: Round 3 | B8: 0 | C8: 0 | D8: 0 | E8: 0
A10: Test Case ID | B10: Test Case Description | C10: Test Case Procedure | D10: Expected Results | E10: Pre-conditions | F10: Round 1 | G10: Test date | H10: Tester | I10: Round 2 | J10: Test date | K10: Tester | L10: Round 3 | M10: Test date | N10: Tester | O10: Note
A11: FR-RPT-01..04
A12: TC-F18-01 | B12: [Main] Block Manager dashboard: occupancy by floor, the SLA rate and target, what is waiting. | C12: Automated (ReportIT.managerDashboard): GET /api/dashboards/manager; check the answer and the database | D12: Block Manager dashboard: occupancy by floor, the SLA rate and target, what is waiting. | E12: Test seed (2 Blocks, 48 students, 7 back-office users); Manager signed in | F12: Passed | G12: 30/10/2026 | H12: CI (mvn verify)
A13: TC-F18-02 | B13: [Main] The dashboard of a Term shows its milestones in order with their progress, its Applications by status, the places per Room Type × Room Class × gender with the Term's prices, and the Deposits issued; Staff cannot read it and an unknown Term is 404. | C13: Automated (TermDashboardIT.termDashboard): GET /api/dashboards/term; check the answer and the database | D13: The dashboard of a Term shows its milestones in order with their progress, its Applications by status, the places per Room Type × Room Class × gender with the Term's prices, and the Deposits issued; Staff cannot read it and an unknown Term is 404. | E13: Test seed (2 Blocks, 48 students, 7 back-office users); Manager signed in | F13: Passed | G13: 30/10/2026 | H13: CI (mvn verify)
A14: TC-F18-03 | B14: [Rule] Exports are CSV files with the screen's columns, written to the Audit Log; scope and permissions. | C14: Automated (ReportIT.exports): GET /api/exports/{report}; check the answer and the database | D14: Exports are CSV files with the screen's columns, written to the Audit Log; scope and permissions. | E14: Test seed (2 Blocks, 48 students, 7 back-office users); Manager signed in | F14: Passed | G14: 30/10/2026 | H14: CI (mvn verify)
A15: TC-F18-04 | B15: [Rule] The Manager's and the Admin's dashboards report the money of Collections and refunds (a paid Deposit without a Bed included) with what is still owed, residents apart from held Beds, the continuing residents the funnel leaves out, the Staff work a Manager decides, and the values of each attention line. | C15: Automated (ReportIT.dashboardsAgreeWithFinance): GET /api/dashboards/admin; GET /api/dashboards/manager; GET /api/dashboards/staff; check the answer and the database | D15: The Manager's and the Admin's dashboards report the money of Collections and refunds (a paid Deposit without a Bed included) with what is still owed, residents apart from held Beds, the continuing residents the funnel leaves out, the Staff work a Manager decides, and the values of each attention line. | E15: Test seed (2 Blocks, 48 students, 7 back-office users); Manager signed in | F15: Passed | G15: 30/10/2026 | H15: CI (mvn verify)
A16: TC-F18-05 | B16: [Exception] The back-office search finds students by code or name, Rooms with or without the dash and request codes inside the user's Blocks; Staff of another Block find neither the Room nor its resident; short queries find nothing and students may not search. | C16: Automated (OperationsIT.search): GET /api/search; check the answer and the database | D16: The back-office search finds students by code or name, Rooms with or without the dash and request codes inside the user's Blocks; Staff of another Block find neither the Room nor its resident; short queries find nothing and students may not search. | E16: Test seed (2 Blocks, 48 students, 7 back-office users); Staff signed in | F16: Passed | G16: 30/10/2026 | H16: CI (mvn verify)

Sheet Workflows
A2: Feature | B2: Main workflows (end to end) | R2: Passed
A3: Test requirement | B3: Each main workflow from the first actor action to the business result, on staging with the demo stages | R3: Failed
A4: Number of TCs | B4: =COUNTA(A12:A1000) -> 5 | R4: Pending
A5: Testing Round | B5: Passed | C5: Failed | D5: Pending | E5: N/A | R5: N/A
A6: Round 1 | B6: =COUNTIF($F10:$F998,B5) -> 0 | C6: =COUNTIF($F10:$F998,C5) -> 0 | D6: =COUNTIF($F10:$F998,D5) -> 5 | E6: =COUNTIF($F10:$F998,E5) -> 0
A7: Round 2 | B7: 0 | C7: 0 | D7: 0 | E7: 0
A8: Round 3 | B8: 0 | C8: 0 | D8: 0 | E8: 0
A10: Test Case ID | B10: Test Case Description | C10: Test Case Procedure | D10: Expected Results | E10: Pre-conditions | F10: Round 1 | G10: Test date | H10: Tester | I10: Round 2 | J10: Test date | K10: Tester | L10: Round 3 | M10: Test date | N10: Tester | O10: Note
A11: WF-01 ... WF-05
A12: TC-WF-01 | B12: WF-01 Registration to residence (owner Lê Thành Minh Trung) | C12: 1. se220001 applies (4-bed, Standard, stay length 2) and claims the Deposit transfer. 2. manager.a confirms the claim and approves the Application. 3. Stage B: se220004 (assigned, unpaid) claims the Balance; manager.a confirms. 4. staff.a1 confirms the Room code; the release job runs. | D12: Application Submitted then Approved; se220004 is a resident (orange Bed) and sees the code; each step notified | E12: Stage A (registration open); se220001 eligible, no Application | F12: Pending
A13: TC-WF-02 | B13: WF-02 Opening a registration period (owner Trần Võ Quang Duy) | C13: 1. manager.a requests a period for the next Term and imports the excluded Rooms from the sample file. 2. admin builds the Term from the request, changes one price with a reason, completes the 7 steps and publishes. | D13: Request Done and linked to the Term; manager.a sees the changed value; students see the registration card and the announcement | E13: Stage 0; manager.a, admin | F13: Pending
A14: TC-WF-03 | B14: WF-03 Term transition of continuing residents (owner Nguyễn Xuân Lộc) | C14: 1. se210006 asks for a room change. 2. staff.a1 approves it with A-603 (stage B). 3. manager.a uploads the enrolled list and resolves groups 1–2. 4. manager.a issues the next-Term fees; se210001 pays and claims. | D14: The next-Term Allocation moves to A-603; fees issued once with count and total; se210001 is Continuing and paid | E14: Stage A (requests window open); se210006 in A-505 | F14: Pending
A15: TC-WF-04 | B15: WF-04 Maintenance with routing and time limits (owner Võ Minh Luân) | C15: 1. se200009 reports an urgent air-conditioner fault with a photo and the item. 2. staff.a2 (routed) starts and resolves it. 3. se200009 confirms. | D15: Assigned at once with the urgent deadline; Closed; the item keeps a repair entry; notifications at each step | E15: Stage A; se200009 in A-801, routing rules of Block A | F15: Pending
A16: TC-WF-05 | B16: WF-05 Monthly Utility, debt and termination (owner Lê Thành Minh Trung) | C16: 1. staff.a1 imports the readings and closes the month. 2. se200001 has an overdue Utility Invoice; the overdue job runs. 3. se200001 claims the transfer; manager.a confirms. | D16: One Utility Invoice per resident split by days; warning 1 sent once; after payment the warning closes | E16: Stage A; staff.a1; meter sample file of Block A | F16: Pending

Sheet State transitions
A2: Feature | B2: State transitions of the main entities | R2: Passed
A3: Test requirement | B3: Every transition of Application, Allocation, next-Term Allocation, Invoice, payment claim and Maintenance Request, and refused transitions | R3: Failed
A4: Number of TCs | B4: =COUNTA(A12:A1000) -> 70 | R4: Pending
A5: Testing Round | B5: Passed | C5: Failed | D5: Pending | E5: N/A | R5: N/A
A6: Round 1 | B6: =COUNTIF($F10:$F998,B5) -> 59 | C6: =COUNTIF($F10:$F998,C5) -> 0 | D6: =COUNTIF($F10:$F998,D5) -> 11 | E6: =COUNTIF($F10:$F998,E5) -> 0
A7: Round 2 | B7: 0 | C7: 0 | D7: 0 | E7: 0
A8: Round 3 | B8: 0 | C8: 0 | D8: 0 | E8: 0
A10: Test Case ID | B10: Test Case Description | C10: Test Case Procedure | D10: Expected Results | E10: Pre-conditions | F10: Round 1 | G10: Test date | H10: Tester | I10: Round 2 | J10: Test date | K10: Tester | L10: Round 3 | M10: Test date | N10: Tester | O10: Note
A11: Report 4 section 3.1
A12: TC-ST-01 | B12: Application: (new) -> Awaiting Deposit (FR-APP-02) | C12: Automated (ApplicationsIT.submitsApplicationWithDeposit): Student submits the wizard | D12: Status is Awaiting Deposit | E12: Entity in state (new) | F12: Passed | G12: 30/10/2026 | H12: CI (mvn verify)
A13: TC-ST-02 | B13: Application: Awaiting Deposit -> Awaiting Roommate (FR-APP-03) | C13: Automated (ApplicationsIT.invitedPairIsSubmittedTogether): Deposit confirmed, invited roommate not ready | D13: Status becomes Awaiting Roommate | E13: Entity in state Awaiting Deposit | F13: Passed | G13: 30/10/2026 | H13: CI (mvn verify)
A14: TC-ST-03 | B14: Application: Awaiting Roommate -> Submitted (FR-APP-03) | C14: Automated (ApplicationsIT.declinedInvitationFallsBackToAutomaticMatching): Roommate's Deposit confirmed, or the roommate declines | D14: Status becomes Submitted | E14: Entity in state Awaiting Roommate | F14: Passed | G14: 30/10/2026 | H14: CI (mvn verify)
A15: TC-ST-04 | B15: Application: Awaiting Deposit -> Submitted (FR-BIL-03) | C15: Automated (PaymentClaimIT.claimStopsTheClockAndBulkConfirmationPays): Manager confirms the Deposit claim | D15: Status becomes Submitted | E15: Entity in state Awaiting Deposit | F15: Passed | G15: 30/10/2026 | H15: CI (mvn verify)
A16: TC-ST-05 | B16: Application: Awaiting Deposit -> Expired (FR-APP-04) | C16: Automated (ApplicationsIT.unpaidApplicationExpires): Deposit window ends without a claim | D16: Status becomes Expired | E16: Entity in state Awaiting Deposit | F16: Passed | G16: 30/10/2026 | H16: CI (mvn verify)
A17: TC-ST-06 | B17: Application: Awaiting Deposit -> Expired (FR-BIL-03) | C17: Automated (PaymentClaimIT.rejectionsGiveTimeBackThenCancel): Second claim rejected | D17: Status becomes Expired | E17: Entity in state Awaiting Deposit | F17: Passed | G17: 30/10/2026 | H17: CI (mvn verify)
A18: TC-ST-07 | B18: Application: Submitted -> Under Review (FR-APP-05) | C18: Automated (AssignmentIT.reviewQueueAndRejection): Manager opens the review | D18: Status becomes Under Review | E18: Entity in state Submitted | F18: Passed | G18: 30/10/2026 | H18: CI (mvn verify)
A19: TC-ST-08 | B19: Application: Submitted -> Approved (FR-APP-05) | C19: Automated (AssignmentIT.assignmentRunToAllocation): Manager approves (bulk) | D19: Status becomes Approved | E19: Entity in state Submitted | F19: Passed | G19: 30/10/2026 | H19: CI (mvn verify)
A20: TC-ST-09 | B20: Application: Under Review -> Approved (FR-APP-05) | C20: Manual on staging: Manager approves after opening the review | D20: Status becomes Approved | E20: Entity in state Under Review | F20: Pending
A21: TC-ST-10 | B21: Application: Under Review -> Rejected (FR-APP-05) | C21: Automated (AssignmentIT.reviewQueueAndRejection): Manager rejects with a note | D21: Status becomes Rejected | E21: Entity in state Under Review | F21: Passed | G21: 30/10/2026 | H21: CI (mvn verify)
A22: TC-ST-11 | B22: Application: Submitted -> Rejected (FR-APP-05) | C22: Manual on staging: Manager rejects from the queue without opening it | D22: Status becomes Rejected | E22: Entity in state Submitted | F22: Pending
A23: TC-ST-12 | B23: Application: Live state -> Cancelled (FR-APP-04) | C23: Automated (ApplicationsIT.cancellationVoidsOrRefunds): Student cancels before the cancel deadline | D23: Status becomes Cancelled | E23: Entity in state Live state | F23: Passed | G23: 30/10/2026 | H23: CI (mvn verify)
A24: TC-ST-13 | B24: Application: Live state -> Rejected (FR-AUTH-08) | C24: Automated (ReconciliationIT.leaversDuringTheTerm): Student not enrolled (leavers list) | D24: Status becomes Rejected | E24: Entity in state Live state | F24: Passed | G24: 30/10/2026 | H24: CI (mvn verify)
A25: TC-ST-14 | B25: Application: Approved -> Waitlisted (FR-ASG-03) | C25: Automated (AssignmentIT.assignmentRunToAllocation): No matching Bed left in the assignment | D25: Status becomes Waitlisted | E25: Entity in state Approved | F25: Passed | G25: 30/10/2026 | H25: CI (mvn verify)
A26: TC-ST-15 | B26: Application: Approved -> Allocated (FR-ASG-03) | C26: Automated (AssignmentIT.assignmentRunToAllocation): Assignment approved for the Block | D26: Status becomes Allocated | E26: Entity in state Approved | F26: Passed | G26: 30/10/2026 | H26: CI (mvn verify)
A27: TC-ST-16 | B27: Application: Waitlisted -> Allocated (FR-APP-07) | C27: Automated (Round2IT.round2Lifecycle): Round-2 offer accepted | D27: Status becomes Allocated | E27: Entity in state Waitlisted | F27: Passed | G27: 30/10/2026 | H27: CI (mvn verify)
A28: TC-ST-17 | B28: Application: Waitlisted -> Cancelled (FR-APP-07) | C28: Automated (Round2IT.round2Lifecycle): Round-2 offer declined or expired | D28: Status becomes Cancelled | E28: Entity in state Waitlisted | F28: Passed | G28: 30/10/2026 | H28: CI (mvn verify)
A29: TC-ST-18 | B29: Application: Waitlisted -> Cancelled (FR-APP-07) | C29: Automated (Round2IT.waitlistedStudentWithdraws): Student withdraws from the waitlist (whole Deposit refunded) | D29: Status becomes Cancelled | E29: Entity in state Waitlisted | F29: Passed | G29: 30/10/2026 | H29: CI (mvn verify)
A30: TC-ST-19 | B30: Application: Waitlisted -> Cancelled (FR-APP-07) | C30: Automated (Round2IT.waitlistEndsWhenCheckInStarts): Check-in starts with no open offer (waitlist ends, Deposit refunded) | D30: Status becomes Cancelled | E30: Entity in state Waitlisted | F30: Passed | G30: 30/10/2026 | H30: CI (mvn verify)
A31: TC-ST-20 | B31: Application: Allocated -> Forfeited (FR-ASG-11) | C31: Automated (ResidenceIT.unpaidBalanceIsForfeited): Balance not paid by its deadline | D31: Status becomes Forfeited | E31: Entity in state Allocated | F31: Passed | G31: 30/10/2026 | H31: CI (mvn verify)
A32: TC-ST-21 | B32: Application: Allocated -> Rejected (FR-AUTH-08) | C32: Manual on staging: Not enrolled before moving in | D32: Status becomes Rejected | E32: Entity in state Allocated | F32: Pending
A33: TC-ST-22 | B33: Allocation: (new) -> Assigned – unpaid (FR-ASG-03) | C33: Automated (AssignmentIT.assignmentRunToAllocation): Assignment approved | D33: Status is Assigned – unpaid | E33: Entity in state (new) | F33: Passed | G33: 30/10/2026 | H33: CI (mvn verify)
A34: TC-ST-23 | B34: Allocation: Assigned – unpaid -> Paid – waiting for the code (FR-BIL-03) | C34: Automated (ResidenceIT.doorCodeIsReleasedToPaidResidents): Balance claim confirmed | D34: Status becomes Paid – waiting for the code | E34: Entity in state Assigned – unpaid | F34: Passed | G34: 30/10/2026 | H34: CI (mvn verify)
A35: TC-ST-24 | B35: Allocation: Assigned – unpaid -> Cancelled (FR-ASG-11) | C35: Automated (ResidenceIT.unpaidBalanceIsForfeited): Balance past its deadline (forfeit) | D35: Status becomes Cancelled | E35: Entity in state Assigned – unpaid | F35: Passed | G35: 30/10/2026 | H35: CI (mvn verify)
A36: TC-ST-25 | B36: Allocation: Assigned – unpaid -> Cancelled (FR-BIL-03) | C36: Automated (ResidenceIT.rejectedClaimsCancelTheBalance): Balance claim rejected twice | D36: Status becomes Cancelled | E36: Entity in state Assigned – unpaid | F36: Passed | G36: 30/10/2026 | H36: CI (mvn verify)
A37: TC-ST-26 | B37: Allocation: Paid – waiting for the code -> Cancelled (FR-AUTH-08) | C37: Manual on staging: Not enrolled before moving in | D37: Status becomes Cancelled | E37: Entity in state Paid – waiting for the code | F37: Pending
A38: TC-ST-27 | B38: Allocation: Paid – waiting for the code -> Resident (FR-ASG-04) | C38: Automated (DoorCodeIT.showsTheStudentTheirCode): Check-in start reached and the Room code confirmed (job) | D38: Status becomes Resident | E38: Entity in state Paid – waiting for the code | F38: Passed | G38: 30/10/2026 | H38: CI (mvn verify)
A39: TC-ST-28 | B39: Allocation: Paid – waiting for the code -> Resident (FR-ASG-04) | C39: Automated (DeskIT.checkInNeedsBalanceAndUtilityDeposit): Checked in at the desk | D39: Status becomes Resident | E39: Entity in state Paid – waiting for the code | F39: Passed | G39: 30/10/2026 | H39: CI (mvn verify)
A40: TC-ST-29 | B40: Allocation: Resident -> Ended (FR-ASG-06) | C40: Automated (DeskIT.checkOutSettlesTheDeposit): Checked out at the desk | D40: Status becomes Ended | E40: Entity in state Resident | F40: Passed | G40: 30/10/2026 | H40: CI (mvn verify)
A41: TC-ST-30 | B41: Allocation: Resident -> Ended (FR-ASG-10) | C41: Automated (OperationalMoveIT.staffMoveAResident): Moved to another Bed | D41: Status becomes Ended | E41: Entity in state Resident | F41: Passed | G41: 30/10/2026 | H41: CI (mvn verify)
A42: TC-ST-31 | B42: Allocation: Resident -> Ended (FR-ASG-10) | C42: Automated (RenewalIT.turnover): The next Term starts for a continuing resident | D42: Status becomes Ended | E42: Entity in state Resident | F42: Passed | G42: 30/10/2026 | H42: CI (mvn verify)
A43: TC-ST-32 | B43: Next-Term Allocation: (new) -> Continuing (FR-ASG-07) | C43: Automated (RenewalIT.windowOpens): M2 opens the window, Terms left in the Stay | D43: Status is Continuing | E43: Entity in state (new) | F43: Passed | G43: 30/10/2026 | H43: CI (mvn verify)
A44: TC-ST-33 | B44: Next-Term Allocation: (new) -> Awaiting extension (FR-ASG-07) | C44: Automated (RenewalIT.windowOpens): M2 opens the window, last Term of the Stay | D44: Status is Awaiting extension | E44: Entity in state (new) | F44: Passed | G44: 30/10/2026 | H44: CI (mvn verify)
A45: TC-ST-34 | B45: Next-Term Allocation: Awaiting extension -> Continuing (FR-REQ-04) | C45: Automated (NextTermRequestIT.extensionsAndEndOfStay): Extension approved | D45: Status becomes Continuing | E45: Entity in state Awaiting extension | F45: Passed | G45: 30/10/2026 | H45: CI (mvn verify)
A46: TC-ST-35 | B46: Next-Term Allocation: Awaiting extension -> Cancelled (FR-ASG-07) | C46: Automated (RenewalIT.notExtendedAtTheDeadline): Not extended by M3 | D46: Status becomes Cancelled | E46: Entity in state Awaiting extension | F46: Passed | G46: 30/10/2026 | H46: CI (mvn verify)
A47: TC-ST-36 | B47: Next-Term Allocation: Continuing -> Continuing (other Bed) (FR-REQ-01, 02) | C47: Automated (RoomChangeIT.staffApprove): Room change or swap approved | D47: Status becomes Continuing (other Bed) | E47: Entity in state Continuing | F47: Passed | G47: 30/10/2026 | H47: CI (mvn verify)
A48: TC-ST-37 | B48: Next-Term Allocation: Continuing -> Cancelled (FR-REQ-04, FR-AUTH-08) | C48: Automated (ReconciliationIT.resolveItems): End of stay or not enrolled | D48: Status becomes Cancelled | E48: Entity in state Continuing | F48: Passed | G48: 30/10/2026 | H48: CI (mvn verify)
A49: TC-ST-38 | B49: Next-Term Allocation: Continuing -> Cancelled (FR-ASG-08) | C49: Automated (RenewalIT.unpaidFeesReleaseTheBed): Next-Term fee unpaid at M7 | D49: Status becomes Cancelled | E49: Entity in state Continuing | F49: Passed | G49: 30/10/2026 | H49: CI (mvn verify)
... A55: TC-ST-44 | B55: Invoice: Unpaid -> Paid (FR-BIL-03) | C55: Automated (PaymentDeskIT.manualConfirmation): Manager confirms a transfer the student did not claim | D55: Status becomes Paid | E55: Entity in state Unpaid | F55: Passed | G55: 30/10/2026 | H55: CI (mvn verify)
A56: TC-ST-45 | B56: Invoice: Overdue -> Paid (FR-BIL-03) | C56: Manual on staging: Manager confirms an overdue debt the student did not claim | D56: Status becomes Paid | E56: Entity in state Overdue | F56: Pending
A57: TC-ST-46 | B57: Invoice: Awaiting confirmation -> Unpaid (FR-BIL-03) | C57: Automated (PaymentClaimIT.rejectionsGiveTimeBackThenCancel): Manager rejects the claim, time left continues | D57: Status becomes Unpaid | E57: Entity in state Awaiting confirmation | F57: Passed | G57: 30/10/2026 | H57: CI (mvn verify)
A58: TC-ST-47 | B58: Invoice: Awaiting confirmation -> Overdue (FR-BIL-03) | C58: Automated (PaymentClaimIT.debtsAreNeverCancelled): Rejected claim of a debt already past due | D58: Status becomes Overdue | E58: Entity in state Awaiting confirmation | F58: Passed | G58: 30/10/2026 | H58: CI (mvn verify)
A59: TC-ST-48 | B59: Invoice: Awaiting confirmation -> Void (FR-BIL-03) | C59: Automated (ResidenceIT.rejectedClaimsCancelTheBalance): Second rejection of a Deposit or Balance claim | D59: Status becomes Void | E59: Entity in state Awaiting confirmation | F59: Passed | G59: 30/10/2026 | H59: CI (mvn verify)
A60: TC-ST-49 | B60: Invoice: Unpaid -> Overdue (FR-BIL-05) | C60: Automated (FinanceIT.overdueAndReminders): Due date passes (Utility, charges) | D60: Status becomes Overdue | E60: Entity in state Unpaid | F60: Passed | G60: 30/10/2026 | H60: CI (mvn verify)
A61: TC-ST-50 | B61: Invoice: Unpaid -> Void (FR-ASG-11, FR-APP-04) | C61: Automated (ApplicationsIT.cancellationVoidsOrRefunds): Forfeit or cancelled Application | D61: Status becomes Void | E61: Entity in state Unpaid | F61: Passed | G61: 30/10/2026 | H61: CI (mvn verify)
A62: TC-ST-51 | B62: Invoice: Overdue -> Void (FR-ASG-06) | C62: Manual on staging: Overdue Utility settled from the Utility Deposit at check-out | D62: Status becomes Void | E62: Entity in state Overdue | F62: Pending
A63: TC-ST-52 | B63: Payment claim: (new) -> Claimed (FR-BIL-02) | C63: Automated (PaymentClaimIT.claimStopsTheClockAndBulkConfirmationPays): Student presses "I have transferred" | D63: Status is Claimed | E63: Entity in state (new) | F63: Passed | G63: 30/10/2026 | H63: CI (mvn verify)
A64: TC-ST-53 | B64: Payment claim: Claimed -> Confirmed (FR-BIL-03) | C64: Automated (PaymentDeskIT.manualConfirmation): Manager confirms | D64: Status becomes Confirmed | E64: Entity in state Claimed | F64: Passed | G64: 30/10/2026 | H64: CI (mvn verify)
A65: TC-ST-54 | B65: Payment claim: (new) -> Confirmed (FR-BIL-03) | C65: Automated (PaymentDeskIT.manualConfirmation): Manager confirms a transfer the student did not claim (claim in the Manager's name) | D65: Status is Confirmed | E65: Entity in state (new) | F65: Passed | G65: 30/10/2026 | H65: CI (mvn verify)
A66: TC-ST-55 | B66: Payment claim: Claimed -> Rejected (FR-BIL-03) | C66: Automated (PaymentClaimIT.rejectionsGiveTimeBackThenCancel): Manager rejects with a reason | D66: Status becomes Rejected | E66: Entity in state Claimed | F66: Passed | G66: 30/10/2026 | H66: CI (mvn verify)
A67: TC-ST-56 | B67: Maintenance Request: (new) -> Submitted (FR-MNT-01) | C67: Automated (MaintenanceIT.studentReportsAndFollows): Resident reports a problem | D67: Status is Submitted | E67: Entity in state (new) | F67: Passed | G67: 30/10/2026 | H67: CI (mvn verify)
A68: TC-ST-57 | B68: Maintenance Request: Submitted -> Assigned (FR-REQ-06) | C68: Automated (RoutingIT.maintenanceFollowsTheRules): Routing rule or Staff assigns, deadline set | D68: Status becomes Assigned | E68: Entity in state Submitted | F68: Passed | G68: 30/10/2026 | H68: CI (mvn verify)
A69: TC-ST-58 | B69: Maintenance Request: Assigned -> Submitted (FR-MNT-02) | C69: Manual on staging: Assignee removed | D69: Status becomes Submitted | E69: Entity in state Assigned | F69: Pending
A70: TC-ST-59 | B70: Maintenance Request: Assigned -> In Progress (FR-MNT-02) | C70: Automated (MaintenanceIT.staffWorkTheRequest): Staff starts the work | D70: Status becomes In Progress | E70: Entity in state Assigned | F70: Passed | G70: 30/10/2026 | H70: CI (mvn verify)
A71: TC-ST-60 | B71: Maintenance Request: In Progress -> Resolved (FR-MNT-02) | C71: Automated (MaintenanceIT.staffWorkTheRequest): Staff marks it fixed | D71: Status becomes Resolved | E71: Entity in state In Progress | F71: Passed | G71: 30/10/2026 | H71: CI (mvn verify)
A72: TC-ST-61 | B72: Maintenance Request: Assigned -> Resolved (FR-MNT-02) | C72: Manual on staging: Staff fixes it without starting it first | D72: Status becomes Resolved | E72: Entity in state Assigned | F72: Pending
A73: TC-ST-62 | B73: Maintenance Request: Resolved -> Closed (FR-MNT-02) | C73: Automated (MaintenanceIT.staffWorkTheRequest): Reporter confirms the fix | D73: Status becomes Closed | E73: Entity in state Resolved | F73: Passed | G73: 30/10/2026 | H73: CI (mvn verify)
A74: TC-ST-63 | B74: Maintenance Request: Resolved -> Assigned (FR-MNT-02) | C74: Automated (MaintenanceIT.staffWorkTheRequest): Reporter reopens (once) | D74: Status becomes Assigned | E74: Entity in state Resolved | F74: Passed | G74: 30/10/2026 | H74: CI (mvn verify)
A75: TC-ST-64 | B75: Maintenance Request: Submitted -> Closed (FR-MNT-02) | C75: Manual on staging: Staff closes a duplicate | D75: Status becomes Closed | E75: Entity in state Submitted | F75: Pending
A76: TC-ST-65 | B76: Maintenance Request: Assigned -> Closed (FR-MNT-02) | C76: Manual on staging: Staff closes it | D76: Status becomes Closed | E76: Entity in state Assigned | F76: Pending
A77: TC-ST-66 | B77: Maintenance Request: In Progress -> Closed (FR-MNT-02) | C77: Manual on staging: Staff closes it | D77: Status becomes Closed | E77: Entity in state In Progress | F77: Pending
A78: TC-ST-67 | B78: Invoice: Paid / Void -> (refused) (FR-BIL-02) | C78: Automated (PaymentClaimIT.claimRules): Claim a Paid or Void Invoice, or a Deposit past its deadline | D78: The API refuses with a clear message; the state is unchanged | E78: Entity in state Paid / Void | F78: Passed | G78: 30/10/2026 | H78: CI (mvn verify)
A79: TC-ST-68 | B79: Invoice: Void -> (refused) (FR-BIL-03) | C79: Automated (PaymentDeskIT.manualConfirmationRules): Confirm a Void Invoice | D79: The API refuses with a clear message; the state is unchanged | E79: Entity in state Void | F79: Passed | G79: 30/10/2026 | H79: CI (mvn verify)
A80: TC-ST-69 | B80: Invoice: Paid -> (refused) (FR-BIL-03) | C80: Automated (PaymentDeskIT.manualConfirmation): Confirm an Invoice a second time | D80: The API refuses with a clear message; the state is unchanged | E80: Entity in state Paid | F80: Passed | G80: 30/10/2026 | H80: CI (mvn verify)
A81: TC-ST-70 | B81: Next-Term Allocation: Continuing (fees issued) -> (refused) (FR-ASG-10) | C81: Automated (OperationalMoveIT.frozenAfterTheFees): Staff move a next-Term Bed after the fees are issued | D81: The API refuses with a clear message; the state is unchanged | E81: Entity in state Continuing (fees issued) | F81: Passed | G81: 30/10/2026 | H81: CI (mvn verify)

Sheet NFRs
A2: Feature | B2: Non-functional requirements | R2: Passed
A3: Test requirement | B3: NFR-01 ... NFR-06: metric, threshold and measurement method | R3: Failed
A4: Number of TCs | B4: =COUNTA(A12:A1000) -> 6 | R4: Pending
A5: Testing Round | B5: Passed | C5: Failed | D5: Pending | E5: N/A | R5: N/A
A6: Round 1 | B6: =COUNTIF($F10:$F998,B5) -> 2 | C6: =COUNTIF($F10:$F998,C5) -> 0 | D6: =COUNTIF($F10:$F998,D5) -> 4 | E6: =COUNTIF($F10:$F998,E5) -> 0
A7: Round 2 | B7: 0 | C7: 0 | D7: 0 | E7: 0
A8: Round 3 | B8: 0 | C8: 0 | D8: 0 | E8: 0
A10: Test Case ID | B10: Test Case Description | C10: Test Case Procedure | D10: Expected Results | E10: Pre-conditions | F10: Round 1 | G10: Test date | H10: Tester | I10: Round 2 | J10: Test date | K10: Tester | L10: Round 3 | M10: Test date | N10: Tester | O10: Note
A11: Report 3 section 4.2
A12: TC-NFR-01 | B12: NFR-01 Performance: p95 of the 10 most used read endpoints with 200 concurrent users on the base data | C12: Load script (Node, 200 virtual users, 10 minutes) against a local server with the production configuration | D12: Threshold: ≤ 1 s, errors < 1 % | E12: Manual (script) | F12: Pending
A13: TC-NFR-02 | B13: NFR-02 Security: Permission and scope tests passing | C13: Automated: TC-AUTH-004, 016, TC-APP-009, TC-BIL-006, TC-INV-003, 007, TC-MNT-003, TC-ASG-021, TC-CFG-012 in mvn verify | D13: Threshold: 100 % | E13: Automated | F13: Passed | G13: 30/10/2026 | H13: CI (mvn verify)
A14: TC-NFR-03 | B14: NFR-03 Integrity: Allocations of one Bed in one Term after parallel commits | C14: Concurrency test: 20 parallel requests for the same Bed, then count active Allocations per Bed and Term | D14: Threshold: 0 duplicates | E14: Automated (planned) | F14: Pending
A15: TC-NFR-04 | B15: NFR-04 Availability: Share of 5-minute health checks answering UP | C15: External uptime check of GET /api/actuator/health every 5 minutes | D15: Threshold: ≥ 99 % from 01/11/2026 | E15: Manual (monitor) | F15: Pending
A16: TC-NFR-05 | B16: NFR-05 Usability (two languages): API messages and web texts with a Vietnamese translation | C16: TC-NTF-036, 037 (MessagesTest) and the scan of every web route in Vietnamese | D16: Threshold: 100 % | E16: Automated + scan | F16: Passed | G16: 30/10/2026 | H16: CI (mvn verify)
A17: TC-NFR-06 | B17: NFR-06 Deployability: Time from push to a healthy production API; rollback time | C17: GitHub Actions run duration of the last 10 deployments; timed rollback with API_TAG | D17: Threshold: ≤ 15 min; ≤ 5 min | E17: Manual (measure) | F17: Pending
